Workbook

Sheet Resumen
C2: 44531 | D2: 45200 | E2: 45444 | F2: 45510 | G2: 45538 | H2: 45573 | I2: 45630 | J2: 45663 | K2: 45694 | L2: 45722 | M2: 45760 | N2: 45782 | O2: 45817 | P2: 45843 | Q2: 45875 | R2: 45905 | S2: 45942 | T2: 45968 | U2: 45998 | V2: 46034 | W2: 46064 | X2: 46093 | Y2: 46118 | Z2: 46153 | AA2: 46180 | AB2: 46208
B3: Casa | C3: =IFERROR( VLOOKUP(B3,'2021-12'!$C$28:$D$33,2,0),0) -> 15000 | D3: =iferror(VLOOKUP(B3,'2023-10'!$C$32:$D$38,2,0),0) -> 28843 | E3: =iferror(VLOOKUP(B3,'2024-06-13'!$C$36:$D$42,2,0),0) -> 31007.45 | F3: =iferror(VLOOKUP(B3,'2024-08-06'!$C$39:$D$45,2,0),0) -> 31525.18 | G3: =iferror(VLOOKUP($B3,Indirect(text(G$2,"yyyy-MM-dd")&"!$C$38:$D$46",TRUE),2,0),0) -> 31785.41 | H3: =iferror(VLOOKUP($B3,Indirect(text(H$2,"yyyy-MM-dd")&"!$C$38:$D$46",TRUE),2,0),0) -> 32046.55 | I3: =iferror(VLOOKUP($B3,Indirect(text(I$2,"yyyy-MM-dd")&"!$C$38:$D$46",TRUE),2,0),0) -> 32608.74 | J3: =iferror(VLOOKUP($B3,Indirect(text(J$2,"yyyy-MM-dd")&"!$C$38:$D$46",TRUE),2,0),0) -> 34313.56 | K3: =iferror(VLOOKUP($B3,Indirect(text(K$2,"yyyy-MM-dd")&"!$C$38:$D$46",TRUE),2,0),0) -> 34619.23 | L3: =iferror(VLOOKUP($B3,Indirect(text(L$2,"yyyy-MM-dd")&"!$C$38:$D$46",TRUE),2,0),0) -> 34925.74 | M3: =iferror(VLOOKUP($B3,Indirect(text(M$2,"yyyy-MM-dd")&"!$C$38:$D$46",TRUE),2,0),0) -> 35233.1 | N3: =iferror(VLOOKUP($B3,Indirect(text(N$2,"yyyy-MM-dd")&"!$C$38:$D$46",TRUE),2,0),0) -> 35541.31 | ... AB3: =iferror(VLOOKUP($B3,Indirect(text(AB$2,"yyyy-MM-dd")&"!$C$38:$D$46",TRUE),2,0),0) -> 40308.34
B4: Inmueble | C4: =IFERROR( VLOOKUP(B4,'2021-12'!$C$28:$D$33,2,0),0) -> 0 | D4: =iferror(VLOOKUP(B4,'2023-10'!$C$32:$D$38,2,0),0) -> 19071.5 | E4: =iferror(VLOOKUP(B4,'2024-06-13'!$C$36:$D$42,2,0),0) -> 20000 | F4: =iferror(VLOOKUP(B4,'2024-08-06'!$C$39:$D$45,2,0),0) -> 20000 | G4: =iferror(VLOOKUP($B4,Indirect(text(G$2,"yyyy-MM-dd")&"!$C$38:$D$46",TRUE),2,0),0) -> 20234.315 | H4: =iferror(VLOOKUP($B4,Indirect(text(H$2,"yyyy-MM-dd")&"!$C$38:$D$46",TRUE),2,0),0) -> 20470.5 | I4: =iferror(VLOOKUP($B4,Indirect(text(I$2,"yyyy-MM-dd")&"!$C$38:$D$46",TRUE),2,0),0) -> 20470.5 | J4: =iferror(VLOOKUP($B4,Indirect(text(J$2,"yyyy-MM-dd")&"!$C$38:$D$46",TRUE),2,0),0) -> 20825.65 | K4: =iferror(VLOOKUP($B4,Indirect(text(K$2,"yyyy-MM-dd")&"!$C$38:$D$46",TRUE),2,0),0) -> 20945.12 | L4: =iferror(VLOOKUP($B4,Indirect(text(L$2,"yyyy-MM-dd")&"!$C$38:$D$46",TRUE),2,0),0) -> 21064.55 | M4: =iferror(VLOOKUP($B4,Indirect(text(M$2,"yyyy-MM-dd")&"!$C$38:$D$46",TRUE),2,0),0) -> 21184.26 | N4: =iferror(VLOOKUP($B4,Indirect(text(N$2,"yyyy-MM-dd")&"!$C$38:$D$46",TRUE),2,0),0) -> 21304.25 | ... AB4: =iferror(VLOOKUP($B4,Indirect(text(AB$2,"yyyy-MM-dd")&"!$C$38:$D$46",TRUE),2,0),0) -> 23001.3
B5: Hereditas | C5: =IFERROR( VLOOKUP(B5,'2021-12'!$C$28:$D$33,2,0),0) -> 0 | D5: =iferror(VLOOKUP(B5,'2023-10'!$C$32:$D$38,2,0),0) -> 0 | E5: =iferror(VLOOKUP(B5,'2024-06-13'!$C$36:$D$42,2,0),0) -> 0 | F5: =iferror(VLOOKUP($B5,Indirect(text(F$2,"yyyy-MM-dd")&"!$C$38:$D$46",TRUE),2,0),0) -> 8000 | G5: =iferror(VLOOKUP($B5,Indirect(text(G$2,"yyyy-MM-dd")&"!$C$38:$D$46",TRUE),2,0),0) -> 8000 | H5: =iferror(VLOOKUP($B5,Indirect(text(H$2,"yyyy-MM-dd")&"!$C$38:$D$46",TRUE),2,0),0) -> 7680 | I5: =iferror(VLOOKUP($B5,Indirect(text(I$2,"yyyy-MM-dd")&"!$C$38:$D$46",TRUE),2,0),0) -> 6363.5 | J5: =iferror(VLOOKUP($B5,Indirect(text(J$2,"yyyy-MM-dd")&"!$C$38:$D$47",TRUE),2,0),0) -> 15919.5 | K5: =iferror(VLOOKUP($B5,Indirect(text(K$2,"yyyy-MM-dd")&"!$C$38:$D$47",TRUE),2,0),0) -> 16523.85 | L5: =iferror(VLOOKUP($B5,Indirect(text(L$2,"yyyy-MM-dd")&"!$C$38:$D$47",TRUE),2,0),0) -> 16160.845 | M5: =iferror(VLOOKUP($B5,Indirect(text(M$2,"yyyy-MM-dd")&"!$C$38:$D$47",TRUE),2,0),0) -> 16790.39 | N5: =iferror(VLOOKUP($B5,Indirect(text(N$2,"yyyy-MM-dd")&"!$C$38:$D$47",TRUE),2,0),0) -> 17219.355 | O5: =iferror(VLOOKUP($B5,Indirect(text(O$2,"yyyy-MM-dd")&"!$C$38:$D$47",TRUE),2,0),0) -> 17738.495 | P5: =iferror(VLOOKUP($B5,Indirect(text(P$2,"yyyy-MM-dd")&"!$C$38:$D$47",TRUE),2,0),0) -> 18279.97 | Q5: =iferror(VLOOKUP($B5,Indirect(text(Q$2,"yyyy-MM-dd")&"!$C$38:$D$47",TRUE),2,0),0) -> 18926.37 | ... AB5: =iferror(VLOOKUP($B5,Indirect(text(AB$2,"yyyy-MM-dd")&"!$C$38:$D$47",TRUE),2,0),0) -> 27559.88
B6: RF | C6: =IFERROR( VLOOKUP(B6,'2021-12'!$C$28:$D$33,2,0),0) -> 17010 | D6: =iferror(VLOOKUP(B6,'2023-10'!$C$32:$D$38,2,0),0) -> 23252 | E6: =iferror(VLOOKUP(B6,'2024-06-13'!$C$36:$D$42,2,0),0) -> 23251.97 | F6: =iferror(VLOOKUP(B6,'2024-08-06'!$C$39:$D$45,2,0),0) -> 21074.69 | G6: =iferror(VLOOKUP($B6,Indirect(text(G$2,"yyyy-MM-dd")&"!$C$38:$D$46",TRUE),2,0),0) -> 22784.73 | H6: =iferror(VLOOKUP($B6,Indirect(text(H$2,"yyyy-MM-dd")&"!$C$38:$D$46",TRUE),2,0),0) -> 23391.62 | I6: =iferror(VLOOKUP($B6,Indirect(text(I$2,"yyyy-MM-dd")&"!$C$38:$D$46",TRUE),2,0),0) -> 25240.08 | J6: =iferror(VLOOKUP($B6,Indirect(text(J$2,"yyyy-MM-dd")&"!$C$38:$D$46",TRUE),2,0),0) -> 29592.03 | K6: =iferror(VLOOKUP($B6,Indirect(text(K$2,"yyyy-MM-dd")&"!$C$38:$D$46",TRUE),2,0),0) -> 31497.21 | L6: =iferror(VLOOKUP($B6,Indirect(text(L$2,"yyyy-MM-dd")&"!$C$38:$D$46",TRUE),2,0),0) -> 32973.37 | M6: =iferror(VLOOKUP($B6,Indirect(text(M$2,"yyyy-MM-dd")&"!$C$38:$D$46",TRUE),2,0),0) -> 28946.33 | N6: =iferror(VLOOKUP($B6,Indirect(text(N$2,"yyyy-MM-dd")&"!$C$38:$D$46",TRUE),2,0),0) -> 32000.9 | ... AB6: =iferror(VLOOKUP($B6,Indirect(text(AB$2,"yyyy-MM-dd")&"!$C$38:$D$46",TRUE),2,0),0) -> 36661.739
B7: PP | C7: =IFERROR( VLOOKUP(B7,'2021-12'!$C$28:$D$33,2,0),0) -> 3865.99 | D7: =iferror(VLOOKUP(B7,'2023-10'!$C$32:$D$38,2,0),0) -> 4773 | E7: =iferror(VLOOKUP(B7,'2024-06-13'!$C$36:$D$42,2,0),0) -> 7728 | F7: =iferror(VLOOKUP(B7,'2024-08-06'!$C$39:$D$45,2,0),0) -> 7380.47 | G7: =iferror(VLOOKUP($B7,Indirect(text(G$2,"yyyy-MM-dd")&"!$C$38:$D$46",TRUE),2,0),0) -> 8001.98 | H7: =iferror(VLOOKUP($B7,Indirect(text(H$2,"yyyy-MM-dd")&"!$C$38:$D$46",TRUE),2,0),0) -> 8042.52 | I7: =iferror(VLOOKUP($B7,Indirect(text(I$2,"yyyy-MM-dd")&"!$C$38:$D$46",TRUE),2,0),0) -> 8515.91 | J7: =iferror(VLOOKUP($B7,Indirect(text(J$2,"yyyy-MM-dd")&"!$C$38:$D$46",TRUE),2,0),0) -> 8316.19 | K7: =iferror(VLOOKUP($B7,Indirect(text(K$2,"yyyy-MM-dd")&"!$C$38:$D$46",TRUE),2,0),0) -> 8456.98 | L7: =iferror(VLOOKUP($B7,Indirect(text(L$2,"yyyy-MM-dd")&"!$C$38:$D$46",TRUE),2,0),0) -> 8145.08 | M7: =iferror(VLOOKUP($B7,Indirect(text(M$2,"yyyy-MM-dd")&"!$C$38:$D$46",TRUE),2,0),0) -> 7442.64 | N7: =iferror(VLOOKUP($B7,Indirect(text(N$2,"yyyy-MM-dd")&"!$C$38:$D$46",TRUE),2,0),0) -> 7892 | ... AB7: =iferror(VLOOKUP($B7,Indirect(text(AB$2,"yyyy-MM-dd")&"!$C$38:$D$46",TRUE),2,0),0) -> 11975.7
B8: PIAS | C8: =IFERROR( VLOOKUP(B8,'2021-12'!$C$28:$D$33,2,0),0) -> 2879.05 | D8: =iferror(VLOOKUP(B8,'2023-10'!$C$32:$D$38,2,0),0) -> 5800 | E8: =iferror(VLOOKUP(B8,'2024-06-13'!$C$36:$D$42,2,0),0) -> 9992 | F8: =iferror(VLOOKUP(B8,'2024-08-06'!$C$39:$D$45,2,0),0) -> 9938.93 | G8: =iferror(VLOOKUP($B8,Indirect(text(G$2,"yyyy-MM-dd")&"!$C$38:$D$46",TRUE),2,0),0) -> 10540.65 | H8: =iferror(VLOOKUP($B8,Indirect(text(H$2,"yyyy-MM-dd")&"!$C$38:$D$46",TRUE),2,0),0) -> 10700.9 | I8: =iferror(VLOOKUP($B8,Indirect(text(I$2,"yyyy-MM-dd")&"!$C$38:$D$46",TRUE),2,0),0) -> 0 | J8: =iferror(VLOOKUP($B8,Indirect(text(J$2,"yyyy-MM-dd")&"!$C$38:$D$46",TRUE),2,0),0) -> 0 | K8: =iferror(VLOOKUP($B8,Indirect(text(K$2,"yyyy-MM-dd")&"!$C$38:$D$46",TRUE),2,0),0) -> 0 | L8: =iferror(VLOOKUP($B8,Indirect(text(L$2,"yyyy-MM-dd")&"!$C$38:$D$46",TRUE),2,0),0) -> 0 | M8: =iferror(VLOOKUP($B8,Indirect(text(M$2,"yyyy-MM-dd")&"!$C$38:$D$46",TRUE),2,0),0) -> 0 | N8: =iferror(VLOOKUP($B8,Indirect(text(N$2,"yyyy-MM-dd")&"!$C$38:$D$46",TRUE),2,0),0) -> 0 | ... AB8: =iferror(VLOOKUP($B8,Indirect(text(AB$2,"yyyy-MM-dd")&"!$C$38:$D$46",TRUE),2,0),0) -> 0
B9: Crypto | C9: =IFERROR( VLOOKUP(B9,'2021-12'!$C$28:$D$33,2,0),0) -> 4400 | D9: =iferror(VLOOKUP(B9,'2023-10'!$C$32:$D$38,2,0),0) -> 630 | E9: =iferror(VLOOKUP(B9,'2024-06-13'!$C$36:$D$42,2,0),0) -> 1370 | F9: =iferror(VLOOKUP(B9,'2024-08-06'!$C$39:$D$47,2,0),0) -> 1370 | G9: =iferror(VLOOKUP($B9,Indirect(text(G$2,"yyyy-MM-dd")&"!$C$38:$D$46",TRUE),2,0),0) -> 1140.04 | H9: =iferror(VLOOKUP($B9,Indirect(text(H$2,"yyyy-MM-dd")&"!$C$38:$D$46",TRUE),2,0),0) -> 1315.78 | I9: =iferror(VLOOKUP($B9,Indirect(text(I$2,"yyyy-MM-dd")&"!$C$38:$D$46",TRUE),2,0),0) -> 2200 | J9: =iferror(VLOOKUP($B9,Indirect(text(J$2,"yyyy-MM-dd")&"!$C$38:$D$46",TRUE),2,0),0) -> 2200 | K9: =iferror(VLOOKUP($B9,Indirect(text(K$2,"yyyy-MM-dd")&"!$C$38:$D$46",TRUE),2,0),0) -> 1982 | L9: =iferror(VLOOKUP($B9,Indirect(text(L$2,"yyyy-MM-dd")&"!$C$38:$D$46",TRUE),2,0),0) -> 1935.08 | M9: =iferror(VLOOKUP($B9,Indirect(text(M$2,"yyyy-MM-dd")&"!$C$38:$D$46",TRUE),2,0),0) -> 1777 | N9: =iferror(VLOOKUP($B9,Indirect(text(N$2,"yyyy-MM-dd")&"!$C$38:$D$46",TRUE),2,0),0) -> 1935.76 | ... AB9: =iferror(VLOOKUP($B9,Indirect(text(AB$2,"yyyy-MM-dd")&"!$C$38:$D$46",TRUE),2,0),0) -> 1180.94
B10: CASH | C10: =IFERROR( VLOOKUP(B10,'2021-12'!$C$28:$D$33,2,0),0) -> 37320 | D10: =iferror(VLOOKUP(B10,'2023-10'!$C$32:$D$38,2,0),0) -> 8527 | E10: =iferror(VLOOKUP(B10,'2024-06-13'!$C$36:$D$42,2,0),0) -> 20112.29 | F10: =iferror(VLOOKUP($B10,Indirect(text(F$2,"yyyy-MM-dd")&"!$C$38:$D$46",TRUE),2,0),0) -> 12035.43 | G10: =iferror(VLOOKUP($B10,Indirect(text(G$2,"yyyy-MM-dd")&"!$C$38:$D$46",TRUE),2,0),0) -> 14556.215 | H10: =iferror(VLOOKUP($B10,Indirect(text(H$2,"yyyy-MM-dd")&"!$C$38:$D$46",TRUE),2,0),0) -> 17074.26 | I10: =iferror(VLOOKUP($B10,Indirect(text(I$2,"yyyy-MM-dd")&"!$C$38:$D$46",TRUE),2,0),0) -> 31141.53 | J10: =iferror(VLOOKUP($B10,Indirect(text(J$2,"yyyy-MM-dd")&"!$C$38:$D$46",TRUE),2,0),0) -> 9458.355 | K10: =iferror(VLOOKUP($B10,Indirect(text(K$2,"yyyy-MM-dd")&"!$C$38:$D$46",TRUE),2,0),0) -> 10771.15 | L10: =iferror(VLOOKUP($B10,Indirect(text(L$2,"yyyy-MM-dd")&"!$C$38:$D$46",TRUE),2,0),0) -> 11914.89 | M10: =iferror(VLOOKUP($B10,Indirect(text(M$2,"yyyy-MM-dd")&"!$C$38:$D$46",TRUE),2,0),0) -> 11206.185 | ... AB10: =iferror(VLOOKUP($B10,Indirect(text(AB$2,"yyyy-MM-dd")&"!$C$38:$D$46",TRUE),2,0),0) -> 30761.015
B11: Total | C11: =SUM(C3:C10) -> 80475.04 | D11: =SUM(D3:D10) -> 90896.5 | E11: =SUM(E3:E10) -> 113461.71 | F11: =SUM(F3:F10) -> 111324.7 | G11: =SUM(G3:G10) -> 117043.34 | H11: =SUM(H3:H10) -> 120722.13 | I11: =SUM(I3:I10) -> 126540.26 | J11: =SUM(J3:J10) -> 120625.29 | ... AB11: =SUM(AB3:AB10) -> 171448.91
G14: {=INDIRECT(text(G2,"yyyy-MM-dd")&"!$C$38")}
C16: 44531 | D16: 45200 | E16: 45444 | F16: 45512 | G16: 45538 | H16: =H2 -> 45573 | I16: =I2 -> 45630 | J16: 45297 | K16: 45328 | L16: 45357 | M16: =M2 -> 45760 | N16: =N2 -> 45782 | O16: =O2 -> 45817 | P16: =P2 -> 45843 | Q16: =Q2 -> 45875 | R16: =R2 -> 45905 | S16: =S2 -> 45942 | T16: =T2 -> 45968 | ... AB16: =AB2 -> 46208
B17: Casa | C17: =C3/C$11 -> 0.1863932 | D17: =D3/D$11 -> 0.31731695 | E17: =E3/E$11 -> 0.27328559 | F17: =F3/F$11 -> 0.28318226 | G17: =G3/G$11 -> 0.27156957 | H17: =H3/H$11 -> 0.26545713 | I17: =I3/I$11 -> 0.25769459 | J17: =J3/J$11 -> 0.28446407 | ... AB17: =AB3/AB$11 -> 0.23510408
B18: Inmueble | C18: =C4/C$11 -> 0 | D18: =D4/D$11 -> 0.20981556 | E18: =E4/E$11 -> 0.17627092 | F18: =F4/F$11 -> 0.17965465 | G18: =G4/G$11 -> 0.17287882 | H18: =H4/H$11 -> 0.16956709 | I18: =I4/I$11 -> 0.16177065 | J18: =J4/J$11 -> 0.17264747 | ... AB18: =AB4/AB$11 -> 0.13415833
B19: Hereditas | C19: =C5/C$11 -> 0 | D19: =D5/D$11 -> 0 | E19: =E5/E$11 -> 0 | F19: =F5/F$11 -> 0.07186186 | G19: =G5/G$11 -> 0.068350749 | H19: =H5/H$11 -> 0.063617168 | I19: =I5/I$11 -> 0.050288343 | J19: =J5/J$11 -> 0.13197482 | ... AB19: =AB5/AB$11 -> 0.16074689
B20: RF | C20: =C6/C$11 -> 0.21136989 | D20: =D6/D$11 -> 0.25580743 | E20: =E6/E$11 -> 0.20493231 | F20: =F6/F$11 -> 0.1893083 | G20: =G6/G$11 -> 0.19466917 | H20: =H6/H$11 -> 0.19376414 | I20: =I6/I$11 -> 0.19946284 | J20: =J6/J$11 -> 0.24532195 | ... AB20: =AB6/AB$11 -> 0.21383477
B21: PP | C21: =C7/C$11 -> 0.048039616 | D21: =D7/D$11 -> 0.052510273 | E21: =E7/E$11 -> 0.068111083 | F21: =F7/F$11 -> 0.066296788 | G21: =G7/G$11 -> 0.068367666 | H21: =H7/H$11 -> 0.066620097 | I21: =I7/I$11 -> 0.067298028 | J21: =J7/J$11 -> 0.068942345 | ... AB21: =AB7/AB$11 -> 0.069849961
B22: PIAS | C22: =C8/C$11 -> 0.035775689 | D22: =D8/D$11 -> 0.063808838 | E22: =E8/E$11 -> 0.088064952 | F22: =F8/F$11 -> 0.089278749 | G22: =G8/G$11 -> 0.090057666 | H22: =H8/H$11 -> 0.088640749 | I22: =I8/I$11 -> 0 | J22: =J8/J$11 -> 0 | ... AB22: =AB8/AB$11 -> 0
B23: Crypto | C23: =C9/C$11 -> 0.054675338 | D23: =D9/D$11 -> 0.0069309599 | E23: =E9/E$11 -> 0.012074558 | F23: =F9/F$11 -> 0.012306344 | G23: =G9/G$11 -> 0.0097403235 | H23: =H9/H$11 -> 0.010899244 | I23: =I9/I$11 -> 0.017385771 | J23: =J9/J$11 -> 0.018238299 | ... AB23: =AB9/AB$11 -> 0.0068879993
B24: CASH | C24: =C10/C$11 -> 0.46374627 | D24: =D10/D$11 -> 0.093809993 | E24: =E10/E$11 -> 0.17726059 | F24: =F10/F$11 -> 0.10811105 | G24: =G10/G$11 -> 0.12436603 | H24: =H10/H$11 -> 0.14143438 | I24: =I10/I$11 -> 0.24609978 | J24: =J10/J$11 -> 0.078411048 | ... AB24: =AB10/AB$11 -> 0.17941796
B25: Total | C25: =C11/$C$11 -> 1 | D25: =D11/$C$11 -> 1.1294993 | E25: =E11/$C$11 -> 1.4098994 | F25: =F11/$C$11 -> 1.3833445 | G25: =G11/$C$11 -> 1.4544055 | H25: =H11/$C$11 -> 1.5001189 | I25: =I11/$C$11 -> 1.5724162 | J25: =J11/$C$11 -> 1.4989155 | ... AB25: =AB11/$C$11 -> 2.1304608

Sheet 2021-12
D2: Date | E2: 44512
A4: Tipo Activo | B4: Activo | C4: Cantidad | D4: NAV | E4: Broker
A5: RF | B5: BBVA | C5: 1692 | D5: 10366 | E5: BBVA
A6: RF | B6: IAG | C6: 650 | D6: 1265 | E6: BBVA
A7: RF | B7: TUB | C7: 700 | D7: 114 | E7: BBVA
A8: PP | B8: Plan Pensiones | D8: 3865.99 | E8: BBVA | F8: =78.75+314.17+34.91 -> 427.83
A9: PIAS | B9: PIAS | D9: 2879.05 | E9: NN
A10: RF | B10: Fondos | D10: 5265 | E10: BKT
A11: Crypto | B11: EARN | D11: 500 | E11: Crypto
A12: Crypto | B12: Metamask | D12: 800 | E12: Crypto
A13: Crypto | B13: WANA | D13: 100 | E13: Crypto
A14: Crypto | B14: AXIE | D14: 3000 | E14: Crypto
A15: CASH | B15: Cta Remunerada 0.2% | D15: 10020 | E15: NN
A16: CASH | B16: Cta Remunerada 5% | D16: 11400 | E16: BKT
A17: CASH | B17: CASH | D17: 15900 | E17: BBVA
A18: Casa | B18: 3C | D18: =175000-160000 -> 15000
C20: RF | D20: =SUMIF($A$5:$A$17,C20,$D$5:$D$17) -> 17010 | E20: =D20/$D$25 -> 0.25979366
C21: PP | D21: =SUMIF($A$5:$A$17,C21,$D$5:$D$17) -> 3865.99 | E21: =D21/$D$25 -> 0.059045248
C22: PIAS | D22: =SUMIF($A$5:$A$17,C22,$D$5:$D$17) -> 2879.05 | E22: =D22/$D$25 -> 0.043971718
C23: Crypto | D23: =SUMIF($A$5:$A$17,C23,$D$5:$D$17) -> 4400 | E23: =D23/$D$25 -> 0.067201181
C24: CASH | D24: =SUMIF($A$5:$A$17,C24,$D$5:$D$17) -> 37320 | E24: =D24/$D$25 -> 0.5699882
D25: =SUM(D20:D24) -> 65475.04
C28: RF | D28: =SUMIF($A$5:$A$17,C28,$D$5:$D$17) -> 17010 | E28: =D28/$D$34 -> 0.21136989
C29: PP | D29: =SUMIF($A$5:$A$17,C29,$D$5:$D$17) -> 3865.99 | E29: =D29/$D$34 -> 0.048039616
C30: PIAS | D30: =SUMIF($A$5:$A$17,C30,$D$5:$D$17) -> 2879.05 | E30: =D30/$D$34 -> 0.035775689
C31: Crypto | D31: =SUMIF($A$5:$A$17,C31,$D$5:$D$17) -> 4400 | E31: =D31/$D$34 -> 0.054675338
C32: CASH | D32: =SUMIF($A$5:$A$18,C32,$D$5:$D$18) -> 37320 | E32: =D32/$D$34 -> 0.46374627
C33: Casa | D33: =SUMIF($A$5:$A$18,C33,$D$5:$D$18) -> 15000 | E33: =D33/$D$34 -> 0.1863932
D34: =SUM(D28:D33) -> 80475.04

Sheet 2023-10
D2: Date | E2: 45220
A4: Tipo Activo | B4: Activo | C4: Cantidad | D4: NAV | E4: Broker
A5: RF | B5: BBVA | C5: 1692 | D5: 12757 | E5: BBVA
A6: RF | B6: IAG | C6: 650 | D6: 1031 | E6: BBVA
A7: RF | B7: TUB | C7: 250 | D7: 716 | E7: BBVA
A8: RF | B8: Grifols | C8: 180 | D8: 1878 | E8: BBVA
A9: PP | B9: Plan Pensiones | D9: 4773 | E9: BKT
A10: PIAS | B10: PIAS | D10: 5800 | E10: NN
A11: RF | B11: Fondos | D11: 6870 | E11: BKT
A12: Crypto | B12: EARN | D12: 630 | E12: Crypto
A13: Crypto | B13: Metamask | D13: 0 | E13: Crypto
A14: Crypto | B14: WANA | D14: 0 | E14: Crypto
A15: Crypto | B15: AXIE | D15: 0 | E15: Crypto
A16: CASH | B16: Comun | D16: 1542 | E16: BKT
A17: CASH | B17: Antonio | D17: 5106 | E17: BKT
A18: CASH | B18: CASH | D18: 1879 | E18: BBVA
A19: Inmueble | B19: AQ | D19: =(110000-71857)*0.5 -> 19071.5
A20: Casa | B20: 3C | D20: =175000-146157 -> 28843
C22: RF | D22: =SUMIF($A$5:$A$19,C22,$D$5:$D$19) -> 23252 | E22: =D22/$D$28 -> 0.37470892
C23: PP | D23: =SUMIF($A$5:$A$19,C23,$D$5:$D$19) -> 4773 | E23: =D23/$D$28 -> 0.076917499
C24: PIAS | D24: =SUMIF($A$5:$A$19,C24,$D$5:$D$19) -> 5800 | E24: =D24/$D$28 -> 0.093467733
C25: Crypto | D25: =SUMIF($A$5:$A$19,C25,$D$5:$D$19) -> 630 | E25: =D25/$D$28 -> 0.01015253
C26: CASH | D26: =SUMIF($A$5:$A$19,C26,$D$5:$D$19) -> 8527 | E26: =D26/$D$28 -> 0.13741368
C27: Inmueble | D27: =SUMIF($A$5:$A$19,C27,$D$5:$D$19) -> 19071.5 | E27: =D27/$D$28 -> 0.30733963
D28: =SUM($D$22:D27) -> 62053.5
C32: RF | D32: =SUMIF($A$5:$A$19,C32,$D$5:$D$19) -> 23252 | E32: =D32/$D$39 -> 0.25580743
C33: PP | D33: =SUMIF($A$5:$A$19,C33,$D$5:$D$19) -> 4773 | E33: =D33/$D$39 -> 0.052510273
C34: PIAS | D34: =SUMIF($A$5:$A$19,C34,$D$5:$D$19) -> 5800 | E34: =D34/$D$39 -> 0.063808838
C35: Crypto | D35: =SUMIF($A$5:$A$19,C35,$D$5:$D$19) -> 630 | E35: =D35/$D$39 -> 0.0069309599
C36: CASH | D36: =SUMIF($A$5:$A$19,C36,$D$5:$D$19) -> 8527 | E36: =D36/$D$39 -> 0.093809993
C37: Inmueble | D37: =SUMIF($A$5:$A$19,C37,$D$5:$D$19) -> 19071.5 | E37: =D37/$D$39 -> 0.20981556
C38: Casa | D38: =SUMIF($A$5:$A$20,C38,$D$5:$D$20) -> 28843 | E38: =D38/$D$39 -> 0.31731695
D39: =SUM(D32:D38) -> 90896.5

Sheet 2024-06-13
D2: Date | E2: 45456
A4: Tipo Activo | B4: Activo | C4: Cantidad | D4: NAV | E4: Broker
A5: RF | B5: BBVA | C5: 792 | D5: 7346.59 | E5: BBVA
A6: RF | B6: IAG | C6: 650 | D6: 1294.48 | E6: BBVA
A7: RF | B7: TUB | C7: 250 | D7: 807.5 | E7: BBVA
A8: RF | B8: Grifols | C8: 180 | D8: 1679.4 | E8: BBVA
A9: RF | B9: BKT | C9: 180 | D9: 1392 | E9: BKT
A10: PP | B10: Plan Pensiones | D10: 7728 | E10: BKT
A11: PIAS | B11: SIALP | D11: 7906 | E11: NN
A12: PIAS | B12: PIAS | D12: 2086 | E12: BKT
A13: RF | B13: Fondos | D13: 10732 | E13: BKT
A14: Crypto | B14: EARN | D14: 1370 | E14: Crypto
A15: Crypto | B15: Metamask | D15: 0 | E15: Crypto
A16: Crypto | B16: WANA | D16: 0 | E16: Crypto
A17: Crypto | B17: AXIE | D17: 0 | E17: Crypto
A18: CASH | B18: Comun | D18: 1190 | E18: BKT
A19: CASH | B19: Antonio | D19: 3400 | E19: BKT
A20: CASH | B20: CASH | D20: 1846.74 | E20: SAN
A21: CASH | B21: CASH | D21: 9955.61 | E21: ING
A22: CASH | B22: CASH | D22: 3719.94 | E22: BBVA
A23: Inmueble | B23: AQ | D23: =(110000-70000)*0.5 -> 20000
A24: Casa | B24: 3C | D24: =175000-143992.55 -> 31007.45
C26: RF | D26: =SUMIF($A$5:$A$24,C26,$D$5:$D$24) -> 23251.97 | E26: =D26/$D$32 -> 0.28199841
C27: PP | D27: =SUMIF($A$5:$A$24,C27,$D$5:$D$24) -> 7728 | E27: =D27/$D$32 -> 0.093724691
C28: PIAS | D28: =SUMIF($A$5:$A$24,C28,$D$5:$D$24) -> 9992 | E28: =D28/$D$32 -> 0.12118234
C29: Crypto | D29: =SUMIF($A$5:$A$24,C29,$D$5:$D$24) -> 1370 | E29: =D29/$D$32 -> 0.016615273
C30: CASH | D30: =SUMIF($A$5:$A$24,C30,$D$5:$D$24) -> 20112.29 | E30: =D30/$D$32 -> 0.24392057
C31: Inmueble | D31: =SUMIF($A$5:$A$24,C31,$D$5:$D$24) -> 20000 | E31: =D31/$D$32 -> 0.24255872
D32: =SUM($D$26:D31) -> 82454.26
C36: RF | D36: =SUMIF($A$5:$A$23,C36,$D$5:$D$23) -> 23251.97 | E36: =D36/$D$43 -> 0.20493231
C37: PP | D37: =SUMIF($A$5:$A$23,C37,$D$5:$D$23) -> 7728 | E37: =D37/$D$43 -> 0.068111083
C38: PIAS | D38: =SUMIF($A$5:$A$23,C38,$D$5:$D$23) -> 9992 | E38: =D38/$D$43 -> 0.088064952
C39: Crypto | D39: =SUMIF($A$5:$A$23,C39,$D$5:$D$23) -> 1370 | E39: =D39/$D$43 -> 0.012074558
C40: CASH | D40: =SUMIF($A$5:$A$23,C40,$D$5:$D$23) -> 20112.29 | E40: =D40/$D$43 -> 0.17726059
C41: Inmueble | D41: =SUMIF($A$5:$A$23,C41,$D$5:$D$23) -> 20000 | E41: =D41/$D$43 -> 0.17627092
C42: Casa | D42: =SUMIF($A$5:$A$24,C42,$D$5:$D$24) -> 31007.45 | E42: =D42/$D$43 -> 0.27328559
D43: =SUM(D36:D42) -> 113461.71

Sheet 2024-08-06
D2: Date | E2: 45510
A4: Tipo Activo | B4: Activo | C4: Cantidad | D4: NAV | E4: Broker
A5: RF | B5: BBVA | C5: 792 | D5: 6884.06 | E5: BBVA
A6: RF | B6: IAG | C6: 650 | D6: 1232.73 | E6: BBVA
A7: RF | B7: TUB | C7: 0 | D7: 0 | E7: BBVA
A8: RF | B8: Grifols | C8: 180 | D8: 1587.96 | E8: BBVA
A9: RF | B9: BKT | C9: 120 | D9: 861.36 | E9: BKT
A10: PP | B10: Plan Pensiones | D10: 7380.47 | E10: BKT
A11: PIAS | B11: SIALP | D11: 7904.82 | E11: NN
A12: PIAS | B12: PIAS | D12: 2034.11 | E12: BKT
A13: RF | B13: Fondos | D13: 10508.58 | E13: BKT
A14: Crypto | B14: EARN | D14: 1370 | E14: Crypto
A15: Crypto | B15: Metamask | D15: 0 | E15: Crypto
A16: Crypto | B16: WANA | D16: 0 | E16: Crypto
A17: Crypto | B17: AXIE | D17: 0 | E17: Crypto
A18: CASH | B18: Comun | D18: =2025.34*0.5 -> 1012.67 | E18: RuralVia
A19: CASH | B19: Comun | D19: 650.55 | E19: BKT
A20: CASH | B20: Antonio | D20: 941.72 | E20: BKT
A21: CASH | B21: CASH | D21: 1661.46 | E21: SAN
A22: CASH | B22: CASH | D22: 3932.62 | E22: ING
A23: CASH | B23: CASH | D23: 3836.41 | E23: BBVA
A24: Inmueble | B24: AQ | D24: =(110000-70000)*0.5 -> 20000
A25: Hereditas | D25: =(16000)/2 -> 8000
A26: Casa | B26: 3C | D26: =175000-143474.82 -> 31525.18
C28: RF | D28: =SUMIF($A$5:$A$26,C28,$D$5:$D$26) -> 21074.69 | E28: =D28/$D$35 -> 0.26409545
C29: PP | D29: =SUMIF($A$5:$A$26,C29,$D$5:$D$26) -> 7380.47 | E29: =D29/$D$35 -> 0.092487649
C30: PIAS | D30: =SUMIF($A$5:$A$26,C30,$D$5:$D$26) -> 9938.93 | E30: =D30/$D$35 -> 0.12454874
C31: Crypto | D31: =SUMIF($A$5:$A$26,C31,$D$5:$D$26) -> 1370 | E31: =D31/$D$35 -> 0.017168023
C32: CASH | D32: =SUMIF($A$5:$A$26,C32,$D$5:$D$26) -> 12035.43 | E32: =D32/$D$35 -> 0.15082083
C33: Inmueble | D33: =SUMIF($A$5:$A$26,C33,$D$5:$D$26) -> 20000 | E33: =D33/$D$35 -> 0.25062807
C34: Hereditas | D34: =SUMIF($A$5:$A$26,C34,$D$5:$D$26) -> 8000
D35: =SUM($D$28:D34) -> 79799.52
C39: RF | D39: =SUMIF($A$5:$A$26,C39,$D$5:$D$26) -> 21074.69 | E39: =D39/$D$47 -> 0.1893083
C40: PP | D40: =SUMIF($A$5:$A$26,C40,$D$5:$D$26) -> 7380.47 | E40: =D40/$D$47 -> 0.066296788
C41: PIAS | D41: =SUMIF($A$5:$A$26,C41,$D$5:$D$26) -> 9938.93 | E41: =D41/$D$47 -> 0.089278749
C42: Crypto | D42: =SUMIF($A$5:$A$26,C42,$D$5:$D$26) -> 1370 | E42: =D42/$D$47 -> 0.012306344
C43: CASH | D43: =SUMIF($A$5:$A$26,C43,$D$5:$D$26) -> 12035.43 | E43: =D43/$D$47 -> 0.10811105
C44: Inmueble | D44: =SUMIF($A$5:$A$26,C44,$D$5:$D$26) -> 20000 | E44: =D44/$D$47 -> 0.17965465
C45: Casa | D45: =SUMIF($A$5:$A$26,C45,$D$5:$D$26) -> 31525.18 | E45: =D45/$D$47 -> 0.28318226
C46: Hereditas | D46: =SUMIF($A$5:$A$26,C46,$D$5:$D$26) -> 8000 | E46: =D46/$D$47 -> 0.07186186
D47: =SUM(D39:D46) -> 111324.7

Sheet 2024-09-03
D2: Date | E2: 45538
A4: Tipo Activo | B4: Activo | C4: Cantidad | D4: NAV | E4: Broker
A5: RF | B5: BBVA | C5: 792 | D5: 7373.52 | E5: BBVA
A6: RF | B6: IAG | C6: 0 | D6: 1403 | E6: BBVA
A7: RF | B7: TUB | D7: 0 | E7: BBVA
A8: RF | B8: Grifols | C8: 180 | D8: 1773 | E8: BBVA
A9: RF | B9: BKT | C9: 120 | D9: 950.88 | E9: BKT
A10: PP | B10: Plan Pensiones | D10: 8001.98 | E10: BKT
A11: PIAS | B11: SIALP | D11: 8430.47 | E11: NN
A12: PIAS | B12: PIAS | D12: 2110.18 | E12: BKT
A13: RF | B13: Fondos | D13: 11284.33 | E13: BKT
A14: Crypto | B14: EARN | D14: 1140.04 | E14: Crypto
A15: Crypto | B15: Metamask | D15: 0 | E15: Crypto
A16: Crypto | B16: WANA | D16: 0 | E16: Crypto
A17: Crypto | B17: AXIE | D17: 0 | E17: Crypto
A18: CASH | B18: Comun | D18: =2025.34*0.5 -> 1012.67 | E18: RuralVia
A19: CASH | B19: Comun | D19: =236.63*0.5 -> 118.315 | E19: BKT
A20: CASH | B20: Antonio | D20: 1040.3 | E20: BKT
A21: CASH | B21: CASH | D21: 2576.22 | E21: SAN
A22: CASH | B22: CASH | D22: 4921.41 | E22: ING
A23: CASH | B23: CASH | D23: 4887.3 | E23: BBVA
A24: Inmueble | B24: AQ | D24: =(110000-69531.37)*0.5 -> 20234.315
A25: Hereditas | D25: =(16000)/2 -> 8000
A26: Casa | B26: 3C | D26: =175000-143214.59 -> 31785.41
C28: RF | D28: =SUMIF($A$5:$A$26,C28,$D$5:$D$26) -> 22784.73 | E28: =D28/$D$35 -> 0.2672447
C29: PP | D29: =SUMIF($A$5:$A$26,C29,$D$5:$D$26) -> 8001.98 | E29: =D29/$D$35 -> 0.093856137
C30: PIAS | D30: =SUMIF($A$5:$A$26,C30,$D$5:$D$26) -> 10540.65 | E30: =D30/$D$35 -> 0.12363249
C31: Crypto | D31: =SUMIF($A$5:$A$26,C31,$D$5:$D$26) -> 1140.04 | E31: =D31/$D$35 -> 0.013371659
C32: CASH | D32: =SUMIF($A$5:$A$26,C32,$D$5:$D$26) -> 14556.215 | E32: =D32/$D$35 -> 0.17073151
C33: Inmueble | D33: =SUMIF($A$5:$A$26,C33,$D$5:$D$26) -> 20234.315 | E33: =D33/$D$35 -> 0.23733059
C34: Hereditas | D34: =SUMIF($A$5:$A$26,C34,$D$5:$D$26) -> 8000
D35: =SUM($D$28:D34) -> 85257.93
C39: RF | D39: =SUMIF($A$5:$A$26,C39,$D$5:$D$26) -> 22784.73 | E39: =D39/$D$47 -> 0.19466917
C40: PP | D40: =SUMIF($A$5:$A$26,C40,$D$5:$D$26) -> 8001.98 | E40: =D40/$D$47 -> 0.068367666
C41: PIAS | D41: =SUMIF($A$5:$A$26,C41,$D$5:$D$26) -> 10540.65 | E41: =D41/$D$47 -> 0.090057666
C42: Crypto | D42: =SUMIF($A$5:$A$26,C42,$D$5:$D$26) -> 1140.04 | E42: =D42/$D$47 -> 0.0097403235
C43: CASH | D43: =SUMIF($A$5:$A$26,C43,$D$5:$D$26) -> 14556.215 | E43: =D43/$D$47 -> 0.12436603
C44: Inmueble | D44: =SUMIF($A$5:$A$26,C44,$D$5:$D$26) -> 20234.315 | E44: =D44/$D$47 -> 0.17287882
C45: Casa | D45: =SUMIF($A$5:$A$26,C45,$D$5:$D$26) -> 31785.41 | E45: =D45/$D$47 -> 0.27156957
C46: Hereditas | D46: =SUMIF($A$5:$A$26,C46,$D$5:$D$26) -> 8000 | E46: =D46/$D$47 -> 0.068350749
D47: =SUM(D39:D46) -> 117043.34

Sheet 2024-10-08
D2: Date | E2: 45538
A4: Tipo Activo | B4: Activo | C4: Cantidad | D4: NAV | E4: Broker
A5: RF | B5: BBVA | C5: 792 | D5: 7362.43 | E5: BBVA
A6: RF | B6: IAG | C6: 0 | D6: 1490.45 | E6: BBVA
A7: RF | B7: TUB | D7: 0 | E7: BBVA
A8: RF | B8: Grifols | C8: 180 | D8: 1828.8 | E8: BBVA
A9: RF | B9: BKT | C9: 120 | D9: 916.32 | E9: BKT
A10: PP | B10: Plan Pensiones | D10: 8042.52 | E10: BKT
A11: PIAS | B11: SIALP | D11: 8570.9 | E11: NN
A12: PIAS | B12: PIAS | D12: 2130 | E12: BKT
A13: RF | B13: Fondos | D13: 11793.62 | E13: BKT
A14: Crypto | B14: EARN | D14: 1315.78 | E14: Crypto
A15: Crypto | B15: Metamask | D15: 0 | E15: Crypto
A16: Crypto | B16: WANA | D16: 0 | E16: Crypto
A17: Crypto | B17: AXIE | D17: 0 | E17: Crypto
A18: CASH | B18: Comun | D18: 1460 | E18: RuralVia
A19: CASH | B19: Comun | D19: =5729/2 -> 2864.5 | E19: BKT
A20: CASH | B20: Antonio | D20: 1590.36 | E20: BKT
A21: CASH | B21: CASH | D21: 2406.8 | E21: SAN
A22: CASH | B22: CASH | D22: 5905.63 | E22: ING
A23: CASH | B23: CASH | D23: 2846.97 | E23: BBVA
A24: Inmueble | B24: AQ | D24: =(110000-69059)*0.5 -> 20470.5
A25: Hereditas | D25: =(75000+21360-81000)/2 -> 7680
A26: Casa | B26: 3C | D26: =175000-142953.45 -> 32046.55
C28: RF | D28: =SUMIF($A$5:$A$26,C28,$D$5:$D$26) -> 23391.62 | E28: =D28/$D$35 -> 0.26378875
C29: PP | D29: =SUMIF($A$5:$A$26,C29,$D$5:$D$26) -> 8042.52 | E29: =D29/$D$35 -> 0.090695995
C30: PIAS | D30: =SUMIF($A$5:$A$26,C30,$D$5:$D$26) -> 10700.9 | E30: =D30/$D$35 -> 0.12067471
C31: Crypto | D31: =SUMIF($A$5:$A$26,C31,$D$5:$D$26) -> 1315.78 | E31: =D31/$D$35 -> 0.014838132
C32: CASH | D32: =SUMIF($A$5:$A$26,C32,$D$5:$D$26) -> 17074.26 | E32: =D32/$D$35 -> 0.19254749
C33: Inmueble | D33: =SUMIF($A$5:$A$26,C33,$D$5:$D$26) -> 20470.5 | E33: =D33/$D$35 -> 0.23084709
C34: Hereditas | D34: =SUMIF($A$5:$A$26,C34,$D$5:$D$26) -> 7680 | E34: =D34/$D$35 -> 0.086607835
D35: =SUM($D$28:D34) -> 88675.58
C39: RF | D39: =SUMIF($A$5:$A$26,C39,$D$5:$D$26) -> 23391.62 | E39: =D39/$D$47 -> 0.19376414
C40: PP | D40: =SUMIF($A$5:$A$26,C40,$D$5:$D$26) -> 8042.52 | E40: =D40/$D$47 -> 0.066620097
C41: PIAS | D41: =SUMIF($A$5:$A$26,C41,$D$5:$D$26) -> 10700.9 | E41: =D41/$D$47 -> 0.088640749
C42: Crypto | D42: =SUMIF($A$5:$A$26,C42,$D$5:$D$26) -> 1315.78 | E42: =D42/$D$47 -> 0.010899244
C43: CASH | D43: =SUMIF($A$5:$A$26,C43,$D$5:$D$26) -> 17074.26 | E43: =D43/$D$47 -> 0.14143438
C44: Inmueble | D44: =SUMIF($A$5:$A$26,C44,$D$5:$D$26) -> 20470.5 | E44: =D44/$D$47 -> 0.16956709
C45: Casa | D45: =SUMIF($A$5:$A$26,C45,$D$5:$D$26) -> 32046.55 | E45: =D45/$D$47 -> 0.26545713
C46: Hereditas | D46: =SUMIF($A$5:$A$26,C46,$D$5:$D$26) -> 7680 | E46: =D46/$D$47 -> 0.063617168
D47: =SUM(D39:D46) -> 120722.13

Sheet 2024-12-04
D2: Date | E2: 45538 | O2: El dinero que tenemos en efectivo no se puede urtilizar para e4sto
A4: Tipo Activo | B4: Activo | C4: Cantidad | D4: NAV | E4: Broker | N4: Opcion 1: | O4: Amortizar
A5: RF | B5: BBVA | C5: 792 | D5: 7269.77 | E5: BBVA
A6: RF | B6: IAG | C6: 0 | D6: 2130.7 | E6: BBVA
A7: RF | B7: TUB | D7: 0 | E7: BBVA
A8: RF | B8: Grifols | C8: 180 | D8: 1521 | E8: BBVA
A9: RF | B9: BKT | C9: 120 | D9: 915.84 | E9: BKT
A10: PP | B10: Plan Pensiones | D10: 8515.91 | E10: BKT
A11: PIAS | B11: SIALP | D11: 0 | E11: NN
A12: PIAS | B12: PIAS | D12: 0 | E12: BKT
A13: RF | B13: Fondos | D13: 13402.77 | E13: BKT
A14: Crypto | B14: EARN | D14: 2200 | E14: Crypto
A15: Crypto | B15: Metamask | D15: 0 | E15: Crypto
A16: Crypto | B16: WANA | D16: 0 | E16: Crypto
A17: Crypto | B17: AXIE | D17: 0 | E17: Crypto
A18: CASH | B18: Comun | D18: =3000/2 -> 1500 | E18: RuralVia | F18: =D18*2 -> 3000
A19: CASH | B19: Comun | D19: =15575/2 -> 7787.5 | E19: BKT | F19: =D19*2 -> 15575 | O19: Cuanto tenemos que devolver de los prestamos
A20: CASH | B20: Antonio | D20: 14100 | E20: BKT | F20: =D20 -> 14100 | O20: 37000 | P20: =O20*1.01 -> 37370
A21: CASH | B21: CASH | D21: 1787.65 | E21: SAN | F21: =D21 -> 1787.65 | N21: Devuelve | O21: 42000 | P21: =O21*1.01 -> 42420
A22: CASH | B22: CASH | D22: 0 | E22: ING | F22: =D22 -> 0
A23: CASH | B23: CASH | D23: 5966.38 | E23: BBVA | F23: =D23 -> 5966.38 | O23: Prestamo que vamos a pedir
A24: Inmueble | B24: AQ | D24: =(110000-69059)*0.5 -> 20470.5
A25: Hereditas | D25: =(75000+19000-37273-44000)/2 -> 6363.5 | F25: =14977 -> 14977 | O25: 38000
A26: Casa | B26: 3C | D26: =175000-142391.26 -> 32608.74
C28: RF | D28: =SUMIF($A$5:$A$26,C28,$D$5:$D$26) -> 25240.08 | E28: =D28/$D$35 -> 0.26870725 | O28: =O21+O20-O25 -> 41000
C29: PP | D29: =SUMIF($A$5:$A$26,C29,$D$5:$D$26) -> 8515.91 | E29: =D29/$D$35 -> 0.090660835
C30: PIAS | D30: =SUMIF($A$5:$A$26,C30,$D$5:$D$26) -> 0 | E30: =D30/$D$35 -> 0 | O30: =F25+F23+F21+F20+F19+F18 -> 55406.03
C31: Crypto | D31: =SUMIF($A$5:$A$26,C31,$D$5:$D$26) -> 2200 | E31: =D31/$D$35 -> 0.023421318 | P31: =O30-O32-O33-O34 -> 36406.03
C32: CASH | D32: =SUMIF($A$5:$A$26,C32,$D$5:$D$26) -> 31141.53 | E32: =D32/$D$35 -> 0.3315344 | O32: 3000 | Q32: 4000
C33: Inmueble | D33: =SUMIF($A$5:$A$26,C33,$D$5:$D$26) -> 20470.5 | E33: =D33/$D$35 -> 0.21793004 | O33: 8000 | Q33: =P31-Q32 -> 32406.03
C34: Hereditas | D34: =SUMIF($A$5:$A$26,C34,$D$5:$D$26) -> 6363.5 | E34: =D34/$D$35 -> 0.067746162 | O34: 8000
D35: =SUM($D$28:D34) -> 93931.52
C39: RF | D39: =SUMIF($A$5:$A$26,C39,$D$5:$D$26) -> 25240.08 | E39: =D39/$D$47 -> 0.19946284
C40: PP | D40: =SUMIF($A$5:$A$26,C40,$D$5:$D$26) -> 8515.91 | E40: =D40/$D$47 -> 0.067298028
C41: PIAS | D41: =SUMIF($A$5:$A$26,C41,$D$5:$D$26) -> 0 | E41: =D41/$D$47 -> 0
C42: Crypto | D42: =SUMIF($A$5:$A$26,C42,$D$5:$D$26) -> 2200 | E42: =D42/$D$47 -> 0.017385771
C43: CASH | D43: =SUMIF($A$5:$A$26,C43,$D$5:$D$26) -> 31141.53 | E43: =D43/$D$47 -> 0.24609978
C44: Inmueble | D44: =SUMIF($A$5:$A$26,C44,$D$5:$D$26) -> 20470.5 | E44: =D44/$D$47 -> 0.16177065
C45: Casa | D45: =SUMIF($A$5:$A$26,C45,$D$5:$D$26) -> 32608.74 | E45: =D45/$D$47 -> 0.25769459
C46: Hereditas | D46: =SUMIF($A$5:$A$26,C46,$D$5:$D$26) -> 6363.5 | E46: =D46/$D$47 -> 0.050288343
D47: =SUM(D39:D46) -> 126540.26
D50: 12
D51: 12

Sheet 2025-01-06
D2: Date | E2: 45538
A4: Tipo Activo | B4: Activo | C4: Cantidad | D4: NAV | E4: Broker
A5: RF | B5: BBVA | C5: 792 | D5: 7717.25 | E5: BBVA
A6: RF | B6: IAG | C6: 650 | D6: 2321.8 | E6: BBVA
A7: RF | B7: Grifols | C7: 180 | D7: 1720.44 | E7: BBVA
A8: RF | B8: BKT | C8: 120 | D8: 924.24 | E8: BBVA
A9: RF | B9: OHLA | C9: 5000 | D9: 2145 | E9: BKT
A10: PP | B10: Plan Pensiones | D10: 8316.19 | E10: BKT
A11: PIAS | B11: SIALP | D11: 0 | E11: NN
A12: PIAS | B12: PIAS | D12: 0 | E12: BKT
A13: RF | B13: Fondos | D13: 13617.33 | E13: BKT
A14: RF | B14: Fondos | D14: 1145.97 | E14: My Investor
A15: Crypto | B15: EARN | D15: 2200 | E15: Crypto
A16: Crypto | B16: Metamask | D16: 0 | E16: Crypto
A17: Crypto | B17: WANA | D17: 0 | E17: Crypto
A18: Crypto | B18: AXIE | D18: 0 | E18: Crypto
A19: CASH | B19: Comun | D19: =3698.56/2 -> 1849.28 | E19: RuralVia
A20: CASH | B20: Comun | D20: =3722.67/2 -> 1861.335 | E20: BKT
A21: CASH | B21: Antonio | D21: 807.81 | E21: BKT
A22: CASH | B22: CASH | D22: 996.68 | E22: SAN
A23: CASH | B23: CASH | D23: 1088.25 | E23: ING
A24: CASH | B24: CASH | D24: 2855 | E24: BBVA
A25: Inmueble | B25: AQ | D25: =(110000-68348.7)*0.5 -> 20825.65
A26: Hereditas | D26: =(75000+14918.69-14868.47-43211.22)/2 -> 15919.5
A27: Casa | B27: 3C | D27: =175000-140686.44 -> 34313.56
C29: RF | D29: =SUMIF($A$5:$A$27,C29,$D$5:$D$27) -> 29592.03 | E29: =D29/$D$36 -> 0.34285064
C30: PP | D30: =SUMIF($A$5:$A$27,C30,$D$5:$D$27) -> 8316.19 | E30: =D30/$D$36 -> 0.096350641
C31: PIAS | D31: =SUMIF($A$5:$A$27,C31,$D$5:$D$27) -> 0 | E31: =D31/$D$36 -> 0
C32: Crypto | D32: =SUMIF($A$5:$A$27,C32,$D$5:$D$27) -> 2200 | E32: =D32/$D$36 -> 0.025489005
C33: CASH | D33: =SUMIF($A$5:$A$27,C33,$D$5:$D$27) -> 9458.355 | E33: =D33/$D$36 -> 0.10958366
C34: Inmueble | D34: =SUMIF($A$5:$A$27,C34,$D$5:$D$27) -> 20825.65 | E34: =D34/$D$36 -> 0.24128414
C35: Hereditas | D35: =SUMIF($A$5:$A$27,C35,$D$5:$D$27) -> 15919.5 | E35: =D35/$D$36 -> 0.18444192
D36: =SUM($D$29:D35) -> 86311.725
C40: RF | D40: =SUMIF($A$5:$A$27,C40,$D$5:$D$27) -> 29592.03 | E40: =D40/$D$48 -> 0.24532195
C41: PP | D41: =SUMIF($A$5:$A$27,C41,$D$5:$D$27) -> 8316.19 | E41: =D41/$D$48 -> 0.068942345
C42: PIAS | D42: =SUMIF($A$5:$A$27,C42,$D$5:$D$27) -> 0 | E42: =D42/$D$48 -> 0
C43: Crypto | D43: =SUMIF($A$5:$A$27,C43,$D$5:$D$27) -> 2200 | E43: =D43/$D$48 -> 0.018238299
C44: CASH | D44: =SUMIF($A$5:$A$27,C44,$D$5:$D$27) -> 9458.355 | E44: =D44/$D$48 -> 0.078411048
C45: Inmueble | D45: =SUMIF($A$5:$A$27,C45,$D$5:$D$27) -> 20825.65 | E45: =D45/$D$48 -> 0.17264747
C46: Casa | D46: =SUMIF($A$5:$A$27,C46,$D$5:$D$27) -> 34313.56 | E46: =D46/$D$48 -> 0.28446407
C47: Hereditas | D47: =SUMIF($A$5:$A$27,C47,$D$5:$D$27) -> 15919.5 | E47: =D47/$D$48 -> 0.13197482
D48: =SUM(D40:D47) -> 120625.29

Sheet 2025-02-06
D2: Date | E2: 45538
A4: Tipo Activo | B4: Activo | C4: Cantidad | D4: NAV | E4: Broker
A5: RF | B5: BBVA | C5: 792 | D5: 9155.52 | E5: BBVA
A6: RF | B6: IAG | C6: 650 | D6: 2817.75 | E6: BBVA
A7: RF | B7: Grifols | C7: 180 | D7: 1521 | E7: BBVA
A8: RF | B8: BKT | C8: 120 | D8: 1008.24 | E8: BKT
A9: RF | B9: OHLA | C9: 5000 | D9: 1810 | E9: BKT
A10: PP | B10: Plan Pensiones | D10: 8456.98 | E10: BKT
A11: PIAS | B11: SIALP | D11: 0 | E11: NN
A12: PIAS | B12: PIAS | D12: 0 | E12: BKT
A13: RF | B13: Fondos | D13: 13870 | E13: BKT
A14: RF | B14: Fondos | D14: 1314.7 | E14: My Investor
A15: Crypto | B15: EARN | D15: 1982 | E15: Crypto
A16: Crypto | B16: Metamask | D16: 0 | E16: Crypto
A17: Crypto | B17: WANA | D17: 0 | E17: Crypto
A18: Crypto | B18: AXIE | D18: 0 | E18: Crypto
A19: CASH | B19: Comun | D19: =4849.12/2 -> 2424.56 | E19: RuralVia
A20: CASH | B20: Comun | D20: =2901.64/2 -> 1450.82 | E20: BKT
A21: CASH | B21: Antonio | D21: 958.61 | E21: BKT
A22: CASH | B22: CASH | D22: 2042.89 | E22: SAN
A23: CASH | B23: CASH | D23: 2126.62 | E23: ING
A24: CASH | B24: CASH | D24: 1767.65 | E24: BBVA
A25: Inmueble | B25: AQ | D25: =(110000-68109.76)*0.5 -> 20945.12
A26: Hereditas | D26: =(75000+15360.48-14366.41-42946.37)/2 -> 16523.85
A27: Casa | B27: 3C | D27: =175000-140380.77 -> 34619.23
C29: RF | D29: =SUMIF($A$5:$A$27,C29,$D$5:$D$27) -> 31497.21 | E29: =D29/$D$36 -> 0.34928475
C30: PP | D30: =SUMIF($A$5:$A$27,C30,$D$5:$D$27) -> 8456.98 | E30: =D30/$D$36 -> 0.093782724
C31: PIAS | D31: =SUMIF($A$5:$A$27,C31,$D$5:$D$27) -> 0 | E31: =D31/$D$36 -> 0
C32: Crypto | D32: =SUMIF($A$5:$A$27,C32,$D$5:$D$27) -> 1982 | E32: =D32/$D$36 -> 0.021979165
C33: CASH | D33: =SUMIF($A$5:$A$27,C33,$D$5:$D$27) -> 10771.15 | E33: =D33/$D$36 -> 0.11944545
C34: Inmueble | D34: =SUMIF($A$5:$A$27,C34,$D$5:$D$27) -> 20945.12 | E34: =D34/$D$36 -> 0.23226854
C35: Hereditas | D35: =SUMIF($A$5:$A$27,C35,$D$5:$D$27) -> 16523.85 | E35: =D35/$D$36 -> 0.18323937
D36: =SUM($D$29:D35) -> 90176.31
C40: RF | D40: =SUMIF($A$5:$A$27,C40,$D$5:$D$27) -> 31497.21 | E40: =D40/$D$48 -> 0.25239051
C41: PP | D41: =SUMIF($A$5:$A$27,C41,$D$5:$D$27) -> 8456.98 | E41: =D41/$D$48 -> 0.067766685
C42: PIAS | D42: =SUMIF($A$5:$A$27,C42,$D$5:$D$27) -> 0 | E42: =D42/$D$48 -> 0
C43: Crypto | D43: =SUMIF($A$5:$A$27,C43,$D$5:$D$27) -> 1982 | E43: =D43/$D$48 -> 0.015881978
C44: CASH | D44: =SUMIF($A$5:$A$27,C44,$D$5:$D$27) -> 10771.15 | E44: =D44/$D$48 -> 0.086310376
C45: Inmueble | D45: =SUMIF($A$5:$A$27,C45,$D$5:$D$27) -> 20945.12 | E45: =D45/$D$48 -> 0.16783549
C46: Casa | D46: =SUMIF($A$5:$A$27,C46,$D$5:$D$27) -> 34619.23 | E46: =D46/$D$48 -> 0.27740759
C47: Hereditas | D47: =SUMIF($A$5:$A$27,C47,$D$5:$D$27) -> 16523.85 | E47: =D47/$D$48 -> 0.13240738
D48: =SUM(D40:D47) -> 124795.54

Sheet 2025-03-06
D2: Date | E2: 45722
A4: Tipo Activo | B4: Activo | C4: Cantidad | D4: NAV | E4: Broker
A5: RF | B5: BBVA | C5: 792 | D5: 10236.6 | E5: BBVA
A6: RF | B6: IAG | C6: 650 | D6: 2538.9 | E6: BBVA
A7: RF | B7: Grifols | C7: 180 | D7: 1947.6 | E7: BBVA
A8: RF | B8: BKT | C8: 120 | D8: 1208.4 | E8: BKT
A9: RF | B9: OHLA | C9: 5000 | D9: 2527.5 | E9: BKT
A10: PP | B10: Plan Pensiones | D10: 8145.08 | E10: BKT
A11: PIAS | B11: SIALP | D11: 0 | E11: NN
A12: PIAS | B12: PIAS | D12: 0 | E12: BKT
A13: RF | B13: Fondos | D13: 13100.67 | E13: BKT
A14: RF | B14: Fondos | D14: 1413.7 | E14: My Investor
A15: Crypto | B15: EARN | D15: 1935.08 | E15: Crypto
A16: Crypto | B16: Metamask | D16: 0 | E16: Crypto
A17: Crypto | B17: WANA | D17: 0 | E17: Crypto
A18: Crypto | B18: AXIE | D18: 0 | E18: Crypto
A19: CASH | B19: Comun | D19: =5555.76/2 -> 2777.88 | E19: RuralVia
A20: CASH | B20: Comun | D20: =2171.08/2 -> 1085.54 | E20: BKT
A21: CASH | B21: Antonio | D21: 2194.55 | E21: BKT
A22: CASH | B22: CASH | D22: 1474.11 | E22: SAN
A23: CASH | B23: CASH | D23: 3075.62 | E23: ING
A24: CASH | B24: CASH | D24: 1307.19 | E24: BBVA
A25: Inmueble | B25: AQ | D25: =(110000-67870.9)*0.5 -> 21064.55
A26: Hereditas | D26: =(75000+51882.94-13881.86-42679.39-38000)/2 -> 16160.845
A27: Casa | B27: 3C | D27: =175000-140074.26 -> 34925.74
C29: RF | D29: =SUMIF($A$5:$A$27,C29,$D$5:$D$27) -> 32973.37 | E29: =D29/$D$36 -> 0.35765273
C30: PP | D30: =SUMIF($A$5:$A$27,C30,$D$5:$D$27) -> 8145.08 | E30: =D30/$D$36 -> 0.088347358
C31: PIAS | D31: =SUMIF($A$5:$A$27,C31,$D$5:$D$27) -> 0 | E31: =D31/$D$36 -> 0
C32: Crypto | D32: =SUMIF($A$5:$A$27,C32,$D$5:$D$27) -> 1935.08 | E32: =D32/$D$36 -> 0.020989261
C33: CASH | D33: =SUMIF($A$5:$A$27,C33,$D$5:$D$27) -> 11914.89 | E33: =D33/$D$36 -> 0.12923741
C34: Inmueble | D34: =SUMIF($A$5:$A$27,C34,$D$5:$D$27) -> 21064.55 | E34: =D34/$D$36 -> 0.22848116
C35: Hereditas | D35: =SUMIF($A$5:$A$27,C35,$D$5:$D$27) -> 16160.845 | E35: =D35/$D$36 -> 0.17529207
D36: =SUM($D$29:D35) -> 92193.815
C40: RF | D40: =SUMIF($A$5:$A$27,C40,$D$5:$D$27) -> 32973.37 | E40: =D40/$D$48 -> 0.25938865
C41: PP | D41: =SUMIF($A$5:$A$27,C41,$D$5:$D$27) -> 8145.08 | E41: =D41/$D$48 -> 0.06407417
C42: PIAS | D42: =SUMIF($A$5:$A$27,C42,$D$5:$D$27) -> 0 | E42: =D42/$D$48 -> 0
C43: Crypto | D43: =SUMIF($A$5:$A$27,C43,$D$5:$D$27) -> 1935.08 | E43: =D43/$D$48 -> 0.01522252
C44: CASH | D44: =SUMIF($A$5:$A$27,C44,$D$5:$D$27) -> 11914.89 | E44: =D44/$D$48 -> 0.093729796
C45: Inmueble | D45: =SUMIF($A$5:$A$27,C45,$D$5:$D$27) -> 21064.55 | E45: =D45/$D$48 -> 0.16570661
C46: Casa | D46: =SUMIF($A$5:$A$27,C46,$D$5:$D$27) -> 34925.74 | E46: =D46/$D$48 -> 0.27474719
C47: Hereditas | D47: =SUMIF($A$5:$A$27,C47,$D$5:$D$27) -> 16160.845 | E47: =D47/$D$48 -> 0.12713107
D48: =SUM(D40:D47) -> 127119.55

Sheet 2025-04-13
D2: Date | E2: 45722
A4: Tipo Activo | B4: Activo | C4: Cantidad | D4: NAV | E4: Broker
A5: RF | B5: BBVA | C5: 792 | D5: 8933.76 | E5: BBVA | F5: 9836
A6: RF | B6: IAG | C6: 650 | D6: 4572.15 | E6: BBVA | F6: 5129.85
A7: RF | B7: Grifols | C7: 180 | D7: 1409.04 | E7: BBVA | F7: 1533.24
A8: RF | B8: BKT | C8: 120 | D8: 1128.24 | E8: BKT | F8: 1231.8
A9: RF | B9: OHLA | C9: 5000 | D9: 0 | E9: BKT
A10: PP | B10: Plan Pensiones | D10: 7442.64 | E10: BKT
A11: PIAS | B11: SIALP | D11: 0 | E11: NN
A12: PIAS | B12: PIAS | D12: 0 | E12: BKT
A13: RF | B13: Fondos | D13: 11514.56 | E13: BKT | F13: 11791.47
A14: RF | B14: Fondos | D14: 1388.58 | E14: My Investor | F14: 1447.7
A15: Crypto | B15: EARN | D15: 1777 | E15: Crypto
A16: Crypto | B16: Metamask | D16: 0 | E16: Crypto
A17: Crypto | B17: WANA | D17: 0 | E17: Crypto
A18: Crypto | B18: AXIE | D18: 0 | E18: Crypto
A19: CASH | B19: Comun | D19: =6045.98/2 -> 3022.99 | E19: RuralVia
A20: CASH | B20: Comun | D20: =1752.31/2 -> 876.155 | E20: BKT
A21: CASH | B21: Antonio | D21: 2760.03 | E21: BKT
A22: CASH | B22: CASH | D22: 1222.19 | E22: SAN
A23: CASH | B23: CASH | D23: 52.75 | E23: ING
A24: CASH | B24: CASH | D24: 3272.07 | E24: BBVA
A25: Inmueble | B25: AQ | D25: =(110000-67631.48)*0.5 -> 21184.26
A26: Hereditas | D26: =(75000+51882.94-13394.8-42410.96-37496.4)/2 -> 16790.39
A27: Casa | B27: 3C | D27: =175000-139766.9 -> 35233.1
C29: RF | D29: =SUMIF($A$5:$A$27,C29,$D$5:$D$27) -> 28946.33 | E29: =D29/$D$36 -> 0.33139541
C30: PP | D30: =SUMIF($A$5:$A$27,C30,$D$5:$D$27) -> 7442.64 | E30: =D30/$D$36 -> 0.085207925
C31: PIAS | D31: =SUMIF($A$5:$A$27,C31,$D$5:$D$27) -> 0 | E31: =D31/$D$36 -> 0
C32: Crypto | D32: =SUMIF($A$5:$A$27,C32,$D$5:$D$27) -> 1777 | E32: =D32/$D$36 -> 0.02034419
C33: CASH | D33: =SUMIF($A$5:$A$27,C33,$D$5:$D$27) -> 11206.185 | E33: =D33/$D$36 -> 0.12829531
C34: Inmueble | D34: =SUMIF($A$5:$A$27,C34,$D$5:$D$27) -> 21184.26 | E34: =D34/$D$36 -> 0.24253045
C35: Hereditas | D35: =SUMIF($A$5:$A$27,C35,$D$5:$D$27) -> 16790.39 | E35: =D35/$D$36 -> 0.19222672
D36: =SUM($D$29:D35) -> 87346.805
C40: RF | D40: =SUMIF($A$5:$A$27,C40,$D$5:$D$27) -> 28946.33 | E40: =D40/$D$48 -> 0.23614254
C41: PP | D41: =SUMIF($A$5:$A$27,C41,$D$5:$D$27) -> 7442.64 | E41: =D41/$D$48 -> 0.06071664
C42: PIAS | D42: =SUMIF($A$5:$A$27,C42,$D$5:$D$27) -> 0 | E42: =D42/$D$48 -> 0
C43: Crypto | D43: =SUMIF($A$5:$A$27,C43,$D$5:$D$27) -> 1777 | E43: =D43/$D$48 -> 0.014496666
C44: CASH | D44: =SUMIF($A$5:$A$27,C44,$D$5:$D$27) -> 11206.185 | E44: =D44/$D$48 -> 0.09141943
C45: Inmueble | D45: =SUMIF($A$5:$A$27,C45,$D$5:$D$27) -> 21184.26 | E45: =D45/$D$48 -> 0.17282001
C46: Casa | D46: =SUMIF($A$5:$A$27,C46,$D$5:$D$27) -> 35233.1 | E46: =D46/$D$48 -> 0.28742966
C47: Hereditas | D47: =SUMIF($A$5:$A$27,C47,$D$5:$D$27) -> 16790.39 | E47: =D47/$D$48 -> 0.13697506
D48: =SUM(D40:D47) -> 122579.9

Sheet 2025-05-05
D2: Date | E2: 45722
A4: Tipo Activo | B4: Activo | C4: Cantidad | D4: NAV | E4: Broker
A5: RF | B5: BBVA | C5: 792 | D5: 9757.44 | E5: BBVA | F5: 9836
A6: RF | B6: IAG | C6: 650 | D6: 5407.05 | E6: BBVA | F6: 5129.85
A7: RF | B7: Grifols | C7: 180 | D7: 1546.56 | E7: BBVA | F7: 1533.24
A8: RF | B8: BKT | C8: 120 | D8: 1263 | E8: BKT | F8: 1231.8
A9: RF | B9: OHLA | C9: 5000 | D9: 0 | E9: BKT
A10: PP | B10: Plan Pensiones | D10: 7892 | E10: BKT
A11: PIAS | B11: SIALP | D11: 0 | E11: NN
A12: PIAS | B12: PIAS | D12: 0 | E12: BKT
A13: RF | B13: Fondos | D13: 12381.2 | E13: BKT | F13: 11791.47
A14: RF | B14: Fondos | D14: 1645.65 | E14: My Investor | F14: 1447.7
A15: Crypto | B15: EARN | D15: 1935.76 | E15: Crypto
A16: Crypto | B16: Metamask | D16: 0 | E16: Crypto
A17: Crypto | B17: WANA | D17: 0 | E17: Crypto
A18: Crypto | B18: AXIE | D18: 0 | E18: Crypto
A19: CASH | B19: Comun | D19: =6768.16/2 -> 3384.08 | E19: RuralVia
A20: CASH | B20: Comun | D20: =1809.79/2 -> 904.895 | E20: BKT
A21: CASH | B21: Antonio | D21: 1795 | E21: BKT
A22: CASH | B22: CASH | D22: 3610.18 | E22: SAN
A23: CASH | B23: CASH | D23: 1675.55 | E23: ING
A24: CASH | B24: CASH | D24: 2308.14 | E24: BBVA
A25: Inmueble | B25: AQ | D25: =(110000-67391.5)*0.5 -> 21304.25
A26: Hereditas | D26: =(75000+51981.42-12905.23-42141.08-37496.4)/2 -> 17219.355
A27: Casa | B27: 3C | D27: =175000-139458.69 -> 35541.31
C29: RF | D29: =SUMIF($A$5:$A$27,C29,$D$5:$D$27) -> 32000.9 | E29: =D29/$D$36 -> 0.34032609
C30: PP | D30: =SUMIF($A$5:$A$27,C30,$D$5:$D$27) -> 7892 | E30: =D30/$D$36 -> 0.083930562
C31: PIAS | D31: =SUMIF($A$5:$A$27,C31,$D$5:$D$27) -> 0 | E31: =D31/$D$36 -> 0
C32: Crypto | D32: =SUMIF($A$5:$A$27,C32,$D$5:$D$27) -> 1935.76 | E32: =D32/$D$36 -> 0.020586597
C33: CASH | D33: =SUMIF($A$5:$A$27,C33,$D$5:$D$27) -> 13677.845 | E33: =D33/$D$36 -> 0.14546239
C34: Inmueble | D34: =SUMIF($A$5:$A$27,C34,$D$5:$D$27) -> 21304.25 | E34: =D34/$D$36 -> 0.22656838
C35: Hereditas | D35: =SUMIF($A$5:$A$27,C35,$D$5:$D$27) -> 17219.355 | E35: =D35/$D$36 -> 0.18312597
D36: =SUM($D$29:D35) -> 94030.11
C40: RF | D40: =SUMIF($A$5:$A$27,C40,$D$5:$D$27) -> 32000.9 | E40: =D40/$D$48 -> 0.24697499
C41: PP | D41: =SUMIF($A$5:$A$27,C41,$D$5:$D$27) -> 7892 | E41: =D41/$D$48 -> 0.060908494
C42: PIAS | D42: =SUMIF($A$5:$A$27,C42,$D$5:$D$27) -> 0 | E42: =D42/$D$48 -> 0
C43: Crypto | D43: =SUMIF($A$5:$A$27,C43,$D$5:$D$27) -> 1935.76 | E43: =D43/$D$48 -> 0.014939714
C44: CASH | D44: =SUMIF($A$5:$A$27,C44,$D$5:$D$27) -> 13677.845 | E44: =D44/$D$48 -> 0.10556221
C45: Inmueble | D45: =SUMIF($A$5:$A$27,C45,$D$5:$D$27) -> 21304.25 | E45: =D45/$D$48 -> 0.1644209
C46: Casa | D46: =SUMIF($A$5:$A$27,C46,$D$5:$D$27) -> 35541.31 | E46: =D46/$D$48 -> 0.27429899
C47: Hereditas | D47: =SUMIF($A$5:$A$27,C47,$D$5:$D$27) -> 17219.355 | E47: =D47/$D$48 -> 0.1328947
D48: =SUM(D40:D47) -> 129571.42

Sheet 2025-06-09
D2: Date | E2: 45722
A4: Tipo Activo | B4: Activo | C4: Cantidad | D4: NAV | E4: Broker
A5: RF | B5: BBVA | C5: 792 | D5: 10503.9 | E5: BBVA | F5: 9836
A6: RF | B6: IAG | C6: 650 | D6: 6599.18 | E6: BBVA | F6: 5129.85
A7: RF | B7: Grifols | C7: 180 | D7: 1868.4 | E7: BBVA | F7: 1533.24
A8: RF | B8: BKT | C8: 120 | D8: 1380 | E8: BKT | F8: 1231.8
A9: RF | B9: OHLA | C9: 5000 | D9: 0 | E9: BKT
A10: PP | B10: Plan Pensiones | D10: 8311.38 | E10: BKT
A11: PIAS | B11: SIALP | D11: 0 | E11: NN
A12: PIAS | B12: PIAS | D12: 0 | E12: BKT
A13: RF | B13: Fondos | D13: 13206.1 | E13: BKT | F13: 11791.47
A14: RF | B14: Fondos | D14: 1877.43 | E14: My Investor | F14: 1447.7
A15: Crypto | B15: EARN | D15: 2184.9 | E15: Crypto
A16: Crypto | B16: Metamask | D16: 0 | E16: Crypto
A17: Crypto | B17: WANA | D17: 0 | E17: Crypto
A18: Crypto | B18: AXIE | D18: 0 | E18: Crypto
A19: CASH | B19: Comun | D19: =7649.86/2 -> 3824.93 | E19: RuralVia
A20: CASH | B20: Comun | D20: =1940.47/2 -> 970.235 | E20: BKT
A21: CASH | B21: Antonio | D21: 578.32 | E21: BKT
A22: CASH | B22: CASH | D22: 5286.89 | E22: SAN
A23: CASH | B23: CASH | D23: 3321.33 | E23: ING
A24: CASH | B24: CASH | D24: 1797.8 | E24: BBVA
A25: Inmueble | B25: AQ | D25: =(110000-67150.96)*0.5 -> 21424.52
A26: Hereditas | D26: =(75000+52003.03-12413.13-41869.73-37243.18)/2 -> 17738.495
A27: Casa | B27: 3C | D27: =175000-139149.63 -> 35850.37
C29: RF | D29: =SUMIF($A$5:$A$27,C29,$D$5:$D$27) -> 35435.01 | E29: =D29/$D$36 -> 0.35128058
C30: PP | D30: =SUMIF($A$5:$A$27,C30,$D$5:$D$27) -> 8311.38 | E30: =D30/$D$36 -> 0.082393834
C31: PIAS | D31: =SUMIF($A$5:$A$27,C31,$D$5:$D$27) -> 0 | E31: =D31/$D$36 -> 0
C32: Crypto | D32: =SUMIF($A$5:$A$27,C32,$D$5:$D$27) -> 2184.9 | E32: =D32/$D$36 -> 0.021659735
C33: CASH | D33: =SUMIF($A$5:$A$27,C33,$D$5:$D$27) -> 15779.505 | E33: =D33/$D$36 -> 0.15642817
C34: Inmueble | D34: =SUMIF($A$5:$A$27,C34,$D$5:$D$27) -> 21424.52 | E34: =D34/$D$36 -> 0.21238932
C35: Hereditas | D35: =SUMIF($A$5:$A$27,C35,$D$5:$D$27) -> 17738.495 | E35: =D35/$D$36 -> 0.17584837
D36: =SUM($D$29:D35) -> 100873.81
C40: RF | D40: =SUMIF($A$5:$A$27,C40,$D$5:$D$27) -> 35435.01 | E40: =D40/$D$48 -> 0.25917149
C41: PP | D41: =SUMIF($A$5:$A$27,C41,$D$5:$D$27) -> 8311.38 | E41: =D41/$D$48 -> 0.060789394
C42: PIAS | D42: =SUMIF($A$5:$A$27,C42,$D$5:$D$27) -> 0 | E42: =D42/$D$48 -> 0
C43: Crypto | D43: =SUMIF($A$5:$A$27,C43,$D$5:$D$27) -> 2184.9 | E43: =D43/$D$48 -> 0.015980348
C44: CASH | D44: =SUMIF($A$5:$A$27,C44,$D$5:$D$27) -> 15779.505 | E44: =D44/$D$48 -> 0.11541122
C45: Inmueble | D45: =SUMIF($A$5:$A$27,C45,$D$5:$D$27) -> 21424.52 | E45: =D45/$D$48 -> 0.15669884
C46: Casa | D46: =SUMIF($A$5:$A$27,C46,$D$5:$D$27) -> 35850.37 | E46: =D46/$D$48 -> 0.26220944
C47: Hereditas | D47: =SUMIF($A$5:$A$27,C47,$D$5:$D$27) -> 17738.495 | E47: =D47/$D$48 -> 0.12973927
D48: =SUM(D40:D47) -> 136724.18

Sheet 2025-07-05
D2: Date | E2: 45722
A4: Tipo Activo | B4: Activo | C4: Cantidad | D4: NAV | E4: Broker
A5: RF | B5: BBVA | C5: 792 | D5: 10242.54 | E5: BBVA | F5: 9836
A6: RF | B6: IAG | C6: 0 | D6: 0 | E6: BBVA | F6: 5129.85
A7: RF | B7: Grifols | C7: 180 | D7: 1899.45 | E7: BBVA | F7: 1533.24
A8: RF | B8: BKT | C8: 120 | D8: 1349.4 | E8: BKT | F8: 1231.8
A9: RF | B9: OHLA | C9: 5000 | D9: 0 | E9: BKT
A10: PP | B10: Plan Pensiones | D10: 8666.3 | E10: BKT
A11: PIAS | B11: SIALP | D11: 0 | E11: NN
A12: PIAS | B12: PIAS | D12: 0 | E12: BKT
A13: RF | B13: Fondos | D13: 13552.87 | E13: BKT | F13: 11791.47
A14: RF | B14: Fondos | D14: 2042.83 | E14: My Investor | F14: 1447.7
A15: Crypto | B15: EARN | D15: 2184.9 | E15: Crypto
A16: Crypto | B16: Metamask | D16: 0 | E16: Crypto
A17: Crypto | B17: WANA | D17: 0 | E17: Crypto
A18: Crypto | B18: AXIE | D18: 0 | E18: Crypto
A19: CASH | B19: Comun | D19: =7628.41/2 -> 3814.205 | E19: RuralVia | F19: =D19+D20 -> 4796.69 | G19: =F19*2 -> 9593.38
A20: CASH | B20: Comun | D20: =1964.97/2 -> 982.485 | E20: BKT
A21: CASH | B21: Antonio | D21: 2790.89 | E21: BKT
A22: CASH | B22: CASH | D22: 8190.94 | E22: SAN
A23: CASH | B23: CASH | D23: 7165.29 | E23: ING
A24: CASH | B24: CASH | D24: 2928.53 | E24: BBVA
A25: Inmueble | B25: AQ | D25: =(110000-66909.86)*0.5 -> 21545.07
A26: Hereditas | D26: =(75000+52064.34-11918.48-41596.91-36989.01)/2 -> 18279.97
A27: Casa | B27: 3C | D27: =175000-138839.72 -> 36160.28
C29: RF | D29: =SUMIF($A$5:$A$27,C29,$D$5:$D$27) -> 29087.09 | E29: =D29/$D$36 -> 0.27535292
C30: PP | D30: =SUMIF($A$5:$A$27,C30,$D$5:$D$27) -> 8666.3 | E30: =D30/$D$36 -> 0.082039523
C31: PIAS | D31: =SUMIF($A$5:$A$27,C31,$D$5:$D$27) -> 0 | E31: =D31/$D$36 -> 0
C32: Crypto | D32: =SUMIF($A$5:$A$27,C32,$D$5:$D$27) -> 2184.9 | E32: =D32/$D$36 -> 0.020683354
C33: CASH | D33: =SUMIF($A$5:$A$27,C33,$D$5:$D$27) -> 25872.34 | E33: =D33/$D$36 -> 0.24492049 | F33: =D33-F19 -> 21075.65
C34: Inmueble | D34: =SUMIF($A$5:$A$27,C34,$D$5:$D$27) -> 21545.07 | E34: =D34/$D$36 -> 0.20395639
C35: Hereditas | D35: =SUMIF($A$5:$A$27,C35,$D$5:$D$27) -> 18279.97 | E35: =D35/$D$36 -> 0.17304732
D36: =SUM($D$29:D35) -> 105635.67
C40: RF | D40: =SUMIF($A$5:$A$27,C40,$D$5:$D$27) -> 29087.09 | E40: =D40/$D$48 -> 0.20513343
C41: PP | D41: =SUMIF($A$5:$A$27,C41,$D$5:$D$27) -> 8666.3 | E41: =D41/$D$48 -> 0.061118107
C42: PIAS | D42: =SUMIF($A$5:$A$27,C42,$D$5:$D$27) -> 0 | E42: =D42/$D$48 -> 0
C43: Crypto | D43: =SUMIF($A$5:$A$27,C43,$D$5:$D$27) -> 2184.9 | E43: =D43/$D$48 -> 0.015408762
C44: CASH | D44: =SUMIF($A$5:$A$27,C44,$D$5:$D$27) -> 25872.34 | E44: =D44/$D$48 -> 0.18246177
C45: Inmueble | D45: =SUMIF($A$5:$A$27,C45,$D$5:$D$27) -> 21545.07 | E45: =D45/$D$48 -> 0.15194418
C46: Casa | D46: =SUMIF($A$5:$A$27,C46,$D$5:$D$27) -> 36160.28 | E46: =D46/$D$48 -> 0.25501631
C47: Hereditas | D47: =SUMIF($A$5:$A$27,C47,$D$5:$D$27) -> 18279.97 | E47: =D47/$D$48 -> 0.12891743
D48: =SUM(D40:D47) -> 141795.95

Sheet 2025-08-06
D2: Date | E2: 45722
A4: Tipo Activo | B4: Activo | C4: Cantidad | D4: NAV | E4: Broker
A5: RF | B5: BBVA | C5: 792 | D5: 11824.56 | E5: BBVA | F5: 9836
A6: RF | B6: IAG | C6: 0 | D6: 0 | E6: BBVA | F6: 5129.85
A7: RF | B7: Grifols | C7: 180 | D7: 2336.4 | E7: BBVA | F7: 1533.24
A8: RF | B8: BKT | C8: 120 | D8: 1500.6 | E8: BKT | F8: 1231.8
A9: RF | B9: OHLA | C9: 5000 | D9: 0 | E9: BKT
A10: PP | B10: Plan Pensiones | D10: 8673.43 | E10: BKT
A11: PIAS | B11: SIALP | D11: 0 | E11: NN
A12: PIAS | B12: PIAS | D12: 0 | E12: BKT
A13: RF | B13: Fondos | D13: 13969.24 | E13: BKT | F13: 11791.47
A14: RF | B14: Fondos | D14: 2230.89 | E14: My Investor | F14: 1447.7
A15: Crypto | B15: EARN | D15: 2320.48 | E15: Crypto
A16: Crypto | B16: Metamask | D16: 0 | E16: Crypto
A17: Crypto | B17: WANA | D17: 0 | E17: Crypto
A18: Crypto | B18: AXIE | D18: 0 | E18: Crypto
A19: CASH | B19: Comun | D19: =+8328.85/2 -> 4164.425 | E19: RuralVia | F19: =D19+D20 -> 5171.8 | G19: =F19*2 -> 10343.6
A20: CASH | B20: Comun | D20: =2014.75/2 -> 1007.375 | E20: BKT
A21: CASH | B21: Antonio | D21: 5116.95 | E21: BKT
A22: CASH | B22: CASH | D22: 7116.35 | E22: SAN
A23: CASH | B23: CASH | D23: 8960.58 | E23: ING
A24: CASH | B24: CASH | D24: 1823.23 | E24: BBVA
A25: Inmueble | B25: AQ | D25: =(110000-66668.2)*0.5 -> 21665.9
A26: Hereditas | D26: =(75000+52085.65-11421.28-40822.62-36989.01)/2 -> 18926.37
A27: Casa | B27: 3C | D27: =175000-138528.95 -> 36471.05
C29: RF | D29: =SUMIF($A$5:$A$27,C29,$D$5:$D$27) -> 31861.69 | E29: =D29/$D$36 -> 0.28540495
C30: PP | D30: =SUMIF($A$5:$A$27,C30,$D$5:$D$27) -> 8673.43 | E30: =D30/$D$36 -> 0.077693301
C31: PIAS | D31: =SUMIF($A$5:$A$27,C31,$D$5:$D$27) -> 0 | E31: =D31/$D$36 -> 0
C32: Crypto | D32: =SUMIF($A$5:$A$27,C32,$D$5:$D$27) -> 2320.48 | E32: =D32/$D$36 -> 0.020785981
C33: CASH | D33: =SUMIF($A$5:$A$27,C33,$D$5:$D$27) -> 28188.91 | E33: =D33/$D$36 -> 0.25250558 | F33: =D33-F19 -> 23017.11
C34: Inmueble | D34: =SUMIF($A$5:$A$27,C34,$D$5:$D$27) -> 21665.9 | E34: =D34/$D$36 -> 0.19407493
C35: Hereditas | D35: =SUMIF($A$5:$A$27,C35,$D$5:$D$27) -> 18926.37 | E35: =D35/$D$36 -> 0.16953526
D36: =SUM($D$29:D35) -> 111636.78
C40: RF | D40: =SUMIF($A$5:$A$27,C40,$D$5:$D$27) -> 31861.69 | E40: =D40/$D$48 -> 0.21512495
C41: PP | D41: =SUMIF($A$5:$A$27,C41,$D$5:$D$27) -> 8673.43 | E41: =D41/$D$48 -> 0.05856159
C42: PIAS | D42: =SUMIF($A$5:$A$27,C42,$D$5:$D$27) -> 0 | E42: =D42/$D$48 -> 0
C43: Crypto | D43: =SUMIF($A$5:$A$27,C43,$D$5:$D$27) -> 2320.48 | E43: =D43/$D$48 -> 0.015667504
C44: CASH | D44: =SUMIF($A$5:$A$27,C44,$D$5:$D$27) -> 28188.91 | E44: =D44/$D$48 -> 0.19032694
C45: Inmueble | D45: =SUMIF($A$5:$A$27,C45,$D$5:$D$27) -> 21665.9 | E45: =D45/$D$48 -> 0.14628464
C46: Casa | D46: =SUMIF($A$5:$A$27,C46,$D$5:$D$27) -> 36471.05 | E46: =D46/$D$48 -> 0.2462466
C47: Hereditas | D47: =SUMIF($A$5:$A$27,C47,$D$5:$D$27) -> 18926.37 | E47: =D47/$D$48 -> 0.12778777
D48: =SUM(D40:D47) -> 148107.83

Sheet 2025-09-05
D2: Date | E2: 45722
A4: Tipo Activo | B4: Activo | C4: Cantidad | D4: NAV | E4: Broker
A5: RF | B5: BBVA | C5: 792 | D5: 12359.16 | E5: BBVA | F5: 9836
A6: RF | B6: IAG | C6: 0 | D6: 0 | E6: BBVA | F6: 5129.85
A7: RF | B7: Grifols | C7: 180 | D7: 2214 | E7: BBVA | F7: 1533.24
A8: RF | B8: BKT | C8: 120 | D8: 1501.8 | E8: BKT | F8: 1231.8
A9: RF | B9: OHLA | C9: 5000 | D9: 0 | E9: BKT
A10: PP | B10: Plan Pensiones | D10: 8928.38 | E10: BKT
A11: PIAS | B11: SIALP | D11: 0 | E11: NN
A12: PIAS | B12: PIAS | D12: 0 | E12: BKT
A13: RF | B13: Fondos | D13: 14499.26 | E13: BKT | F13: 11791.47
A14: RF | B14: Fondos | D14: 2432.6 | E14: My Investor | F14: 1447.7
A15: Crypto | B15: EARN | D15: 2336.04 | E15: Crypto | O15: 43 | P15: 50
A16: Crypto | B16: Metamask | D16: 0 | E16: Crypto | O16: 38 | P16: 67
A17: Crypto | B17: WANA | D17: 0 | E17: Crypto | O17: 37
A18: Crypto | B18: AXIE | D18: 0 | E18: Crypto
A19: CASH | B19: Comun | D19: =+8824.3/2 -> 4412.15 | E19: RuralVia | F19: =D19+D20 -> 5336.45 | G19: =F19*2 -> 10672.9
A20: CASH | B20: Comun | D20: =1848.6/2 -> 924.3 | E20: BKT
A21: CASH | B21: Antonio | D21: 3456.86 | E21: BKT
A22: CASH | B22: CASH | D22: 1564.51 | E22: SAN
A23: CASH | B23: CASH | D23: 18586.65 | E23: ING
A24: CASH | B24: CASH | D24: 504.19 | E24: BBVA
A25: Inmueble | B25: AQ | D25: =(110000-66425.97)*0.5 -> 21787.015
A26: Hereditas | D26: =(75000+50634.46-10921.51-40544.74-36477.81)/2 -> 18845.2
A27: Casa | B27: 3C | D27: =175000-138217.32 -> 36782.68
C29: RF | D29: =SUMIF($A$5:$A$27,C29,$D$5:$D$27) -> 33006.82 | E29: =D29/$D$36 -> 0.28864197
C30: PP | D30: =SUMIF($A$5:$A$27,C30,$D$5:$D$27) -> 8928.38 | E30: =D30/$D$36 -> 0.078077961
C31: PIAS | D31: =SUMIF($A$5:$A$27,C31,$D$5:$D$27) -> 0 | E31: =D31/$D$36 -> 0
C32: Crypto | D32: =SUMIF($A$5:$A$27,C32,$D$5:$D$27) -> 2336.04 | E32: =D32/$D$36 -> 0.020428481
C33: CASH | D33: =SUMIF($A$5:$A$27,C33,$D$5:$D$27) -> 29448.66 | E33: =D33/$D$36 -> 0.25752615 | F33: =D33-F19 -> 24112.21
C34: Inmueble | D34: =SUMIF($A$5:$A$27,C34,$D$5:$D$27) -> 21787.015 | E34: =D34/$D$36 -> 0.19052568
C35: Hereditas | D35: =SUMIF($A$5:$A$27,C35,$D$5:$D$27) -> 18845.2 | E35: =D35/$D$36 -> 0.16479975
D36: =SUM($D$29:D35) -> 114352.12
C40: RF | D40: =SUMIF($A$5:$A$27,C40,$D$5:$D$27) -> 33006.82 | E40: =D40/$D$48 -> 0.21839326
C41: PP | D41: =SUMIF($A$5:$A$27,C41,$D$5:$D$27) -> 8928.38 | E41: =D41/$D$48 -> 0.059075609
C42: PIAS | D42: =SUMIF($A$5:$A$27,C42,$D$5:$D$27) -> 0 | E42: =D42/$D$48 -> 0
C43: Crypto | D43: =SUMIF($A$5:$A$27,C43,$D$5:$D$27) -> 2336.04 | E43: =D43/$D$48 -> 0.015456666
C44: CASH | D44: =SUMIF($A$5:$A$27,C44,$D$5:$D$27) -> 29448.66 | E44: =D44/$D$48 -> 0.1948503
C45: Inmueble | D45: =SUMIF($A$5:$A$27,C45,$D$5:$D$27) -> 21787.015 | E45: =D45/$D$48 -> 0.14415618
C46: Casa | D46: =SUMIF($A$5:$A$27,C46,$D$5:$D$27) -> 36782.68 | E46: =D46/$D$48 -> 0.24337665
C47: Hereditas | D47: =SUMIF($A$5:$A$27,C47,$D$5:$D$27) -> 18845.2 | E47: =D47/$D$48 -> 0.12469134
D48: =SUM(D40:D47) -> 151134.8

Sheet 2025-10-12
D2: Date | E2: 45722
A4: Tipo Activo | B4: Activo | C4: Cantidad | D4: NAV | E4: Broker
A5: RF | B5: BBVA | C5: 792 | D5: 6189.68 | E5: BBVA | F5: 9836
A6: RF | B6: IAG | C6: 0 | D6: 0 | E6: BBVA | F6: 5129.85
A7: RF | B7: Grifols | C7: 180 | D7: 2134.8 | E7: BBVA | F7: 1533.24
A8: RF | B8: BKT | C8: 120 | D8: 1604.4 | E8: BKT | F8: 1231.8
A9: RF | B9: OHLA | C9: 5000 | D9: 0 | E9: BKT
A10: PP | B10: Plan Pensiones | D10: 8969.58 | E10: BKT
A11: PIAS | B11: SIALP | D11: 0 | E11: NN
A12: PIAS | B12: PIAS | D12: 0 | E12: BKT
A13: RF | B13: Fondos | D13: 15250.85 | E13: BKT | F13: 11791.47
A14: RF | B14: Fondos | D14: 2432.6 | E14: My Investor | F14: 1447.7
A15: Crypto | B15: EARN | D15: 2336.04 | E15: Crypto | O15: 43 | P15: 50
A16: Crypto | B16: Metamask | D16: 0 | E16: Crypto | O16: 38 | P16: 67
A17: Crypto | B17: WANA | D17: 0 | E17: Crypto | O17: 37
A18: Crypto | B18: AXIE | D18: 0 | E18: Crypto
A19: CASH | B19: Comun | D19: =+9154.66/2 -> 4577.33 | E19: RuralVia | F19: =D19+D20 -> 5293.93 | G19: =F19*2 -> 10587.86
A20: CASH | B20: Comun | D20: =1433.2/2 -> 716.6 | E20: BKT
A21: CASH | B21: Antonio | D21: 2134.21 | E21: BKT
A22: CASH | B22: CASH | D22: 4681.25 | E22: SAN
A23: CASH | B23: CASH | D23: =14748.36+828.58 -> 15576.94 | E23: ING
A24: CASH | B24: CASH | D24: =5529.82 -> 5529.82 | E24: BBVA
A25: Inmueble | B25: AQ | D25: =(110000-66183.18)*0.5 -> 21908.41
A26: Hereditas | D26: =(75000+49919.05-10419.16-40264.75-35962.77)/2 -> 19136.185
A27: Casa | B27: 3C | D27: =175000-137904.83 -> 37095.17
C29: RF | D29: =SUMIF($A$5:$A$27,C29,$D$5:$D$27) -> 27612.33 | E29: =D29/$D$36 -> 0.24397109
C30: PP | D30: =SUMIF($A$5:$A$27,C30,$D$5:$D$27) -> 8969.58 | E30: =D30/$D$36 -> 0.079251488
C31: PIAS | D31: =SUMIF($A$5:$A$27,C31,$D$5:$D$27) -> 0 | E31: =D31/$D$36 -> 0
C32: Crypto | D32: =SUMIF($A$5:$A$27,C32,$D$5:$D$27) -> 2336.04 | E32: =D32/$D$36 -> 0.02064028
C33: CASH | D33: =SUMIF($A$5:$A$27,C33,$D$5:$D$27) -> 33216.15 | E33: =D33/$D$36 -> 0.29348412 | F33: =D33-F19 -> 27922.22
C34: Inmueble | D34: =SUMIF($A$5:$A$27,C34,$D$5:$D$27) -> 21908.41 | E34: =D34/$D$36 -> 0.19357362
C35: Hereditas | D35: =SUMIF($A$5:$A$27,C35,$D$5:$D$27) -> 19136.185 | E35: =D35/$D$36 -> 0.16907939
D36: =SUM($D$29:D35) -> 113178.7
C40: RF | D40: =SUMIF($A$5:$A$27,C40,$D$5:$D$27) -> 27612.33 | E40: =D40/$D$48 -> 0.18374672
C41: PP | D41: =SUMIF($A$5:$A$27,C41,$D$5:$D$27) -> 8969.58 | E41: =D41/$D$48 -> 0.059688223
C42: PIAS | D42: =SUMIF($A$5:$A$27,C42,$D$5:$D$27) -> 0 | E42: =D42/$D$48 -> 0
C43: Crypto | D43: =SUMIF($A$5:$A$27,C43,$D$5:$D$27) -> 2336.04 | E43: =D43/$D$48 -> 0.015545218
C44: CASH | D44: =SUMIF($A$5:$A$27,C44,$D$5:$D$27) -> 33216.15 | E44: =D44/$D$48 -> 0.22103744
C45: Inmueble | D45: =SUMIF($A$5:$A$27,C45,$D$5:$D$27) -> 21908.41 | E45: =D45/$D$48 -> 0.14578989
C46: Casa | D46: =SUMIF($A$5:$A$27,C46,$D$5:$D$27) -> 37095.17 | E46: =D46/$D$48 -> 0.24685044
C47: Hereditas | D47: =SUMIF($A$5:$A$27,C47,$D$5:$D$27) -> 19136.185 | E47: =D47/$D$48 -> 0.12734207
D48: =SUM(D40:D47) -> 150273.86

Sheet 2025-11-07
D2: Date | E2: 45722
A4: Tipo Activo | B4: Activo | C4: Cantidad | D4: NAV | E4: Broker
A5: RF | B5: BBVA | C5: 792 | D5: 6955.06 | E5: BBVA | F5: 9836
A6: RF | B6: IAG | C6: 0 | D6: 0 | E6: BBVA | F6: 5129.85
A7: RF | B7: Grifols | C7: 180 | D7: 1872 | E7: BBVA | F7: 1533.24
A8: RF | B8: BKT | C8: 120 | D8: 1623 | E8: BKT | F8: 1231.8
A9: RF | B9: OHLA | C9: 5000 | D9: 0 | E9: BKT
A10: PP | B10: Plan Pensiones | D10: 9179.7 | E10: BKT
A11: PIAS | B11: SIALP | D11: 0 | E11: NN
A12: PIAS | B12: PIAS | D12: 0 | E12: BKT
A13: RF | B13: Fondos | D13: 15425.52 | E13: BKT | F13: 11791.47
A14: RF | B14: Fondos | D14: 2923.12 | E14: My Investor | F14: 1447.7
A15: Crypto | B15: EARN | D15: 2152.21 | E15: Crypto | O15: 43 | P15: 50
A16: Crypto | B16: Metamask | D16: 0 | E16: Crypto | O16: 38 | P16: 67
A17: Crypto | B17: WANA | D17: 0 | E17: Crypto | O17: 37
A18: Crypto | B18: AXIE | D18: 0 | E18: Crypto
A19: CASH | B19: Comun | D19: =+10180.13/2 -> 5090.065 | E19: RuralVia | F19: =D19+D20 -> 5615.985 | G19: =F19*2 -> 11231.97
A20: CASH | B20: Comun | D20: =1051.84/2 -> 525.92 | E20: BKT
A21: CASH | B21: Antonio | D21: 4253.08 | E21: BKT
A22: CASH | B22: CASH | D22: 3512 | E22: SAN
A23: CASH | B23: CASH | D23: 16378.09 | E23: ING
A24: CASH | B24: CASH | D24: 4341.29 | E24: BBVA
A25: Inmueble | B25: AQ | D25: =(110000-65939.83)*0.5 -> 22030.085
A26: Hereditas | D26: =(75000+50374.19-9914.21-39983.24-35962.77)/2 -> 19756.985
A27: Casa | B27: 3C | D27: =175000-137591.48 -> 37408.52
C29: RF | D29: =SUMIF($A$5:$A$27,C29,$D$5:$D$27) -> 28798.7 | E29: =D29/$D$36 -> 0.24822587
C30: PP | D30: =SUMIF($A$5:$A$27,C30,$D$5:$D$27) -> 9179.7 | E30: =D30/$D$36 -> 0.079122982
C31: PIAS | D31: =SUMIF($A$5:$A$27,C31,$D$5:$D$27) -> 0 | E31: =D31/$D$36 -> 0
C32: Crypto | D32: =SUMIF($A$5:$A$27,C32,$D$5:$D$27) -> 2152.21 | E32: =D32/$D$36 -> 0.018550636
C33: CASH | D33: =SUMIF($A$5:$A$27,C33,$D$5:$D$27) -> 34100.445 | E33: =D33/$D$36 -> 0.29392343 | F33: =D33-F19 -> 28484.46
C34: Inmueble | D34: =SUMIF($A$5:$A$27,C34,$D$5:$D$27) -> 22030.085 | E34: =D34/$D$36 -> 0.18988486
C35: Hereditas | D35: =SUMIF($A$5:$A$27,C35,$D$5:$D$27) -> 19756.985 | E35: =D35/$D$36 -> 0.17029223
D36: =SUM($D$29:D35) -> 116018.12
C40: RF | D40: =SUMIF($A$5:$A$27,C40,$D$5:$D$27) -> 28798.7 | E40: =D40/$D$48 -> 0.18770338
C41: PP | D41: =SUMIF($A$5:$A$27,C41,$D$5:$D$27) -> 9179.7 | E41: =D41/$D$48 -> 0.059831198
C42: PIAS | D42: =SUMIF($A$5:$A$27,C42,$D$5:$D$27) -> 0 | E42: =D42/$D$48 -> 0
C43: Crypto | D43: =SUMIF($A$5:$A$27,C43,$D$5:$D$27) -> 2152.21 | E43: =D43/$D$48 -> 0.014027616
C44: CASH | D44: =SUMIF($A$5:$A$27,C44,$D$5:$D$27) -> 34100.445 | E44: =D44/$D$48 -> 0.22225895
C45: Inmueble | D45: =SUMIF($A$5:$A$27,C45,$D$5:$D$27) -> 22030.085 | E45: =D45/$D$48 -> 0.14358709
C46: Casa | D46: =SUMIF($A$5:$A$27,C46,$D$5:$D$27) -> 37408.52 | E46: =D46/$D$48 -> 0.24382023
C47: Hereditas | D47: =SUMIF($A$5:$A$27,C47,$D$5:$D$27) -> 19756.985 | E47: =D47/$D$48 -> 0.12877154
D48: =SUM(D40:D47) -> 153426.64

Sheet 2025-12-07
D2: Date | E2: 45722
A4: Tipo Activo | B4: Activo | C4: Cantidad | D4: NAV | E4: Broker
A5: RF | B5: BBVA | C5: 792 | D5: 7399 | E5: BBVA | F5: 9836
A6: RF | B6: IAG | C6: 0 | D6: 0 | E6: BBVA | F6: 5129.85
A7: RF | B7: Grifols | C7: 180 | D7: 1938.6 | E7: BBVA | F7: 1533.24
A8: RF | B8: BKT | C8: 120 | D8: 1638.6 | E8: BKT | F8: 1231.8
A9: RF | B9: OHLA | C9: 5000 | D9: 0 | E9: BKT
A10: PP | B10: Plan Pensiones | D10: 9355.62 | E10: BKT
A11: PIAS | B11: SIALP | D11: 0 | E11: NN
A12: PIAS | B12: PIAS | D12: 0 | E12: BKT
A13: RF | B13: Fondos | D13: 16721.75 | E13: BKT | F13: 11791.47
A14: RF | B14: Fondos | D14: 3060.78 | E14: My Investor | F14: 1447.7
A15: Crypto | B15: EARN | D15: 1636.42 | E15: Crypto | O15: 43 | P15: 50
A16: Crypto | B16: Metamask | D16: 0 | E16: Crypto | O16: 38 | P16: 67
A17: Crypto | B17: WANA | D17: 0 | E17: Crypto | O17: 37
A18: Crypto | B18: AXIE | D18: 0 | E18: Crypto
A19: CASH | B19: Comun | D19: =+10866.97/2 -> 5433.485 | E19: RuralVia | F19: =D19+D20 -> 5680.49 | G19: =F19*2 -> 11360.98
A20: CASH | B20: Comun | D20: =494.01/2 -> 247.005 | E20: BKT
A21: CASH | B21: Antonio | D21: 3258.95 | E21: BKT
A22: CASH | B22: CASH | D22: 2679.58 | E22: SAN
A23: CASH | B23: CASH | D23: 18018.07 | E23: ING
A24: CASH | B24: CASH | D24: 3008.7 | E24: BBVA
A25: Inmueble | B25: AQ | D25: =(110000-65695.91)*0.5 -> 22152.045
A26: Hereditas | D26: =(75000+50435.5-9406.65-39700.21-35703.8)/2 -> 20312.42
A27: Casa | B27: 3C | D27: =175000-137231.39 -> 37768.61
C29: RF | D29: =SUMIF($A$5:$A$27,C29,$D$5:$D$27) -> 30758.73 | E29: =D29/$D$36 -> 0.26320777
C30: PP | D30: =SUMIF($A$5:$A$27,C30,$D$5:$D$27) -> 9355.62 | E30: =D30/$D$36 -> 0.080057658
C31: PIAS | D31: =SUMIF($A$5:$A$27,C31,$D$5:$D$27) -> 0 | E31: =D31/$D$36 -> 0
C32: Crypto | D32: =SUMIF($A$5:$A$27,C32,$D$5:$D$27) -> 1636.42 | E32: =D32/$D$36 -> 0.014003129
C33: CASH | D33: =SUMIF($A$5:$A$27,C33,$D$5:$D$27) -> 32645.79 | E33: =D33/$D$36 -> 0.27935567 | F33: =D33-F19 -> 26965.3
C34: Inmueble | D34: =SUMIF($A$5:$A$27,C34,$D$5:$D$27) -> 22152.045 | E34: =D34/$D$36 -> 0.18955888
C35: Hereditas | D35: =SUMIF($A$5:$A$27,C35,$D$5:$D$27) -> 20312.42 | E35: =D35/$D$36 -> 0.17381689
D36: =SUM($D$29:D35) -> 116861.02
C40: RF | D40: =SUMIF($A$5:$A$27,C40,$D$5:$D$27) -> 30758.73 | E40: =D40/$D$48 -> 0.19891873
C41: PP | D41: =SUMIF($A$5:$A$27,C41,$D$5:$D$27) -> 9355.62 | E41: =D41/$D$48 -> 0.060503409
C42: PIAS | D42: =SUMIF($A$5:$A$27,C42,$D$5:$D$27) -> 0 | E42: =D42/$D$48 -> 0
C43: Crypto | D43: =SUMIF($A$5:$A$27,C43,$D$5:$D$27) -> 1636.42 | E43: =D43/$D$48 -> 0.010582836
C44: CASH | D44: =SUMIF($A$5:$A$27,C44,$D$5:$D$27) -> 32645.79 | E44: =D44/$D$48 -> 0.21112247
C45: Inmueble | D45: =SUMIF($A$5:$A$27,C45,$D$5:$D$27) -> 22152.045 | E45: =D45/$D$48 -> 0.14325873
C46: Casa | D46: =SUMIF($A$5:$A$27,C46,$D$5:$D$27) -> 37768.61 | E46: =D46/$D$48 -> 0.24425208
C47: Hereditas | D47: =SUMIF($A$5:$A$27,C47,$D$5:$D$27) -> 20312.42 | E47: =D47/$D$48 -> 0.13136175
D48: =SUM(D40:D47) -> 154629.64

Sheet 2026-01-12
D2: Date | E2: 45722
A4: Tipo Activo | B4: Activo | C4: Cantidad | D4: NAV | E4: Broker
A5: RF | B5: BBVA | C5: 792 | D5: 8118.32 | E5: BBVA | F5: 9836
A6: RF | B6: IAG | C6: 0 | D6: 0 | E6: BBVA | F6: 5129.85
A7: RF | B7: Grifols | C7: 180 | D7: 1995.3 | E7: BBVA | F7: 1533.24
A8: RF | B8: BKT | C8: 120 | D8: 1686 | E8: BKT | F8: 1231.8
A9: RF | B9: OHLA | C9: 5000 | D9: 0 | E9: BKT
A10: PP | B10: Plan Pensiones | D10: 10969.93 | E10: ING
A11: PIAS | B11: SIALP | D11: 0 | E11: NN
A12: PIAS | B12: PIAS | D12: 0 | E12: BKT
A13: RF | B13: Fondos | D13: 16181.41 | E13: BKT | F13: 11791.47
A14: RF | B14: Fondos | D14: 3280.53 | E14: My Investor | F14: 1447.7
A15: Crypto | B15: EARN | D15: 1636.42 | E15: Crypto | O15: 43 | P15: 50
A16: Crypto | B16: Metamask | D16: 0 | E16: Crypto | O16: 38 | P16: 67
A17: Crypto | B17: WANA | D17: 0 | E17: Crypto | O17: 37
A18: Crypto | B18: AXIE | D18: 0 | E18: Crypto
A19: CASH | B19: Comun | D19: =+10546.21/2 -> 5273.105 | E19: RuralVia | F19: =D19+D20 -> 5520.11 | G19: =F19*2 -> 11040.22
A20: CASH | B20: Comun | D20: =494.01/2 -> 247.005 | E20: BKT
A21: CASH | B21: Antonio | D21: 5542.68 | E21: BKT
A22: CASH | B22: CASH | D22: 662.12 | E22: SAN
A23: CASH | B23: CASH | D23: 15104.78 | E23: ING
A24: CASH | B24: CASH | D24: 544.26 | E24: BBVA
A25: Inmueble | B25: AQ | D25: =(110000-65451.42)*0.5 -> 22274.29
A26: Hereditas | D26: =(75000+50271.81-8896.47-39415.64-35443.86)/2 -> 20757.92
A27: Casa | B27: 3C | D27: =175000-136870.62 -> 38129.38
C29: RF | D29: =SUMIF($A$5:$A$27,C29,$D$5:$D$27) -> 31261.56 | E29: =D29/$D$36 -> 0.27356652
C30: PP | D30: =SUMIF($A$5:$A$27,C30,$D$5:$D$27) -> 10969.93 | E30: =D30/$D$36 -> 0.095996668
C31: PIAS | D31: =SUMIF($A$5:$A$27,C31,$D$5:$D$27) -> 0 | E31: =D31/$D$36 -> 0
C32: Crypto | D32: =SUMIF($A$5:$A$27,C32,$D$5:$D$27) -> 1636.42 | E32: =D32/$D$36 -> 0.014320134
C33: CASH | D33: =SUMIF($A$5:$A$27,C33,$D$5:$D$27) -> 27373.95 | E33: =D33/$D$36 -> 0.23954647 | F33: =D33-F19 -> 21853.84
C34: Inmueble | D34: =SUMIF($A$5:$A$27,C34,$D$5:$D$27) -> 22274.29 | E34: =D34/$D$36 -> 0.1949199
C35: Hereditas | D35: =SUMIF($A$5:$A$27,C35,$D$5:$D$27) -> 20757.92 | E35: =D35/$D$36 -> 0.18165031
D36: =SUM($D$29:D35) -> 114274.07
C40: RF | D40: =SUMIF($A$5:$A$27,C40,$D$5:$D$27) -> 31261.56 | E40: =D40/$D$48 -> 0.2051237
C41: PP | D41: =SUMIF($A$5:$A$27,C41,$D$5:$D$27) -> 10969.93 | E41: =D41/$D$48 -> 0.071979539
C42: PIAS | D42: =SUMIF($A$5:$A$27,C42,$D$5:$D$27) -> 0 | E42: =D42/$D$48 -> 0
C43: Crypto | D43: =SUMIF($A$5:$A$27,C43,$D$5:$D$27) -> 1636.42 | E43: =D43/$D$48 -> 0.010737421
C44: CASH | D44: =SUMIF($A$5:$A$27,C44,$D$5:$D$27) -> 27373.95 | E44: =D44/$D$48 -> 0.17961503
C45: Inmueble | D45: =SUMIF($A$5:$A$27,C45,$D$5:$D$27) -> 22274.29 | E45: =D45/$D$48 -> 0.14615345
C46: Casa | D46: =SUMIF($A$5:$A$27,C46,$D$5:$D$27) -> 38129.38 | E46: =D46/$D$48 -> 0.25018712
C47: Hereditas | D47: =SUMIF($A$5:$A$27,C47,$D$5:$D$27) -> 20757.92 | E47: =D47/$D$48 -> 0.13620374
D48: =SUM(D40:D47) -> 152403.45

Sheet 2026-02-11
D2: Date | E2: 45722
A4: Tipo Activo | B4: Activo | C4: Cantidad | D4: NAV | E4: Broker
A5: RF | B5: BBVA | C5: 792 | D5: 7981.12 | E5: BBVA | F5: 9836
A6: RF | B6: IAG | C6: 0 | D6: 0 | E6: BBVA | F6: 5129.85
A7: RF | B7: Grifols | C7: 180 | D7: 1995.3 | E7: BBVA | F7: 1533.24
A8: RF | B8: BKT | C8: 120 | D8: 1701 | E8: BKT | F8: 1231.8
A9: RF | B9: OHLA | C9: 5000 | D9: 0 | E9: BKT
A10: PP | B10: Plan Pensiones | D10: 10737.67 | E10: ING
A11: PIAS | B11: SIALP | D11: 0 | E11: NN
A12: PIAS | B12: PIAS | D12: 0 | E12: BKT
A13: RF | B13: Fondos | D13: 15911.07 | E13: BKT | F13: 11791.47
A14: RF | B14: Fondos | D14: 3472.9 | E14: My Investor | F14: 1447.7
A15: Crypto | B15: EARN | D15: 1156.47 | E15: Crypto | O15: 43 | P15: 50
A16: Crypto | B16: Metamask | D16: 0 | E16: Crypto | O16: 38 | P16: 67
A17: Crypto | B17: WANA | D17: 0 | E17: Crypto | O17: 37
A18: Crypto | B18: AXIE | D18: 0 | E18: Crypto
A19: CASH | B19: Comun | D19: =+10808.69/2 -> 5404.345 | E19: RuralVia | F19: =D19+D20 -> 6603.215 | G19: =F19*2 -> 13206.43
A20: CASH | B20: Comun | D20: =1198.87 -> 1198.87 | E20: BKT
A21: CASH | B21: Antonio | D21: 1435.52 | E21: BKT
A22: CASH | B22: CASH | D22: 247.57 | E22: SAN
A23: CASH | B23: CASH | D23: 16813.43 | E23: ING
A24: CASH | B24: CASH | D24: 646.04 | E24: BBVA
A25: Inmueble | B25: AQ | D25: =(110000-65206.36)*0.5 -> 22396.82
A26: Hereditas | D26: =(75000+50333.12-6383.66-39129-35182.94)/2 -> 22318.76
A27: Casa | B27: 3C | D27: =175000-136509.17 -> 38490.83
C29: RF | D29: =SUMIF($A$5:$A$27,C29,$D$5:$D$27) -> 31061.39 | E29: =D29/$D$36 -> 0.27386919
C30: PP | D30: =SUMIF($A$5:$A$27,C30,$D$5:$D$27) -> 10737.67 | E30: =D30/$D$36 -> 0.094674351
C31: PIAS | D31: =SUMIF($A$5:$A$27,C31,$D$5:$D$27) -> 0 | E31: =D31/$D$36 -> 0
C32: Crypto | D32: =SUMIF($A$5:$A$27,C32,$D$5:$D$27) -> 1156.47 | E32: =D32/$D$36 -> 0.01019663
C33: CASH | D33: =SUMIF($A$5:$A$27,C33,$D$5:$D$27) -> 25745.775 | E33: =D33/$D$36 -> 0.22700125 | F33: =D33-F19 -> 19142.56
C34: Inmueble | D34: =SUMIF($A$5:$A$27,C34,$D$5:$D$27) -> 22396.82 | E34: =D34/$D$36 -> 0.19747342
C35: Hereditas | D35: =SUMIF($A$5:$A$27,C35,$D$5:$D$27) -> 22318.76 | E35: =D35/$D$36 -> 0.19678516
D36: =SUM($D$29:D35) -> 113416.88
C40: RF | D40: =SUMIF($A$5:$A$27,C40,$D$5:$D$27) -> 31061.39 | E40: =D40/$D$48 -> 0.20447539
C41: PP | D41: =SUMIF($A$5:$A$27,C41,$D$5:$D$27) -> 10737.67 | E41: =D41/$D$48 -> 0.070685482
C42: PIAS | D42: =SUMIF($A$5:$A$27,C42,$D$5:$D$27) -> 0 | E42: =D42/$D$48 -> 0
C43: Crypto | D43: =SUMIF($A$5:$A$27,C43,$D$5:$D$27) -> 1156.47 | E43: =D43/$D$48 -> 0.0076129774
C44: CASH | D44: =SUMIF($A$5:$A$27,C44,$D$5:$D$27) -> 25745.775 | E44: =D44/$D$48 -> 0.169483
C45: Inmueble | D45: =SUMIF($A$5:$A$27,C45,$D$5:$D$27) -> 22396.82 | E45: =D45/$D$48 -> 0.14743701
C46: Casa | D46: =SUMIF($A$5:$A$27,C46,$D$5:$D$27) -> 38490.83 | E46: =D46/$D$48 -> 0.25338298
C47: Hereditas | D47: =SUMIF($A$5:$A$27,C47,$D$5:$D$27) -> 22318.76 | E47: =D47/$D$48 -> 0.14692315
D48: =SUM(D40:D47) -> 151907.71

Sheet 2026-03-12
D2: Date | E2: 45722
A4: Tipo Activo | B4: Activo | C4: Cantidad | D4: NAV | E4: Broker
A5: RF | B5: BBVA | C5: 792 | D5: 7344.12 | E5: BBVA | F5: 9836
A6: RF | B6: IAG | C6: 0 | D6: 0 | E6: BBVA | F6: 5129.85
A7: RF | B7: Grifols | C7: 180 | D7: 1683.9 | E7: BBVA | F7: 1533.24
A8: RF | B8: BKT | C8: 120 | D8: 1644.6 | E8: BKT | F8: 1231.8
A9: RF | B9: OHLA | C9: 5000 | D9: 0 | E9: BKT
A10: PP | B10: Plan Pensiones | D10: 10684.41 | E10: ING
A11: PIAS | B11: SIALP | D11: 0 | E11: NN
A12: PIAS | B12: PIAS | D12: 0 | E12: BKT
A13: RF | B13: Fondos | D13: 16161.36 | E13: BKT | F13: 11791.47
A14: RF | B14: Fondos | D14: 3582.34 | E14: My Investor | F14: 1447.7
A15: Crypto | B15: EARN | D15: 1256.13 | E15: Crypto | O15: 43 | P15: 50
A16: Crypto | B16: Metamask | D16: 0 | E16: Crypto | O16: 38 | P16: 67
A17: Crypto | B17: WANA | D17: 0 | E17: Crypto | O17: 37
A18: Crypto | B18: AXIE | D18: 0 | E18: Crypto
A19: CASH | B19: Comun | D19: =+12023.44/2 -> 6011.72 | E19: RuralVia | F19: =D19+D20 -> 6416.87 | G19: =F19*2 -> 12833.74
A20: CASH | B20: Comun | D20: =810.3/2 -> 405.15 | E20: BKT
A21: CASH | B21: Antonio | D21: 4155.52 | E21: BKT
A22: CASH | B22: CASH | D22: 665.16 | E22: SAN
A23: CASH | B23: CASH | D23: 2986.17 | E23: ING
A24: CASH | B24: CASH | D24: 353.99 | E24: BBVA
A25: Inmueble | B25: AQ | D25: =(110000-64960.73)*0.5 -> 22519.635
A26: Hereditas | D26: =(75000+50799.04-5858.55-38541.3-34921.05)/2 -> 23239.07
A27: Casa | B27: 3C + AB | D27: =175000+10000-136147.04 -> 48852.96
C29: RF | D29: =SUMIF($A$5:$A$27,C29,$D$5:$D$27) -> 30416.32 | E29: =D29/$D$36 -> 0.29618609
C30: PP | D30: =SUMIF($A$5:$A$27,C30,$D$5:$D$27) -> 10684.41 | E30: =D30/$D$36 -> 0.10404196
C31: PIAS | D31: =SUMIF($A$5:$A$27,C31,$D$5:$D$27) -> 0 | E31: =D31/$D$36 -> 0
C32: Crypto | D32: =SUMIF($A$5:$A$27,C32,$D$5:$D$27) -> 1256.13 | E32: =D32/$D$36 -> 0.012231862
C33: CASH | D33: =SUMIF($A$5:$A$27,C33,$D$5:$D$27) -> 14577.71 | E33: =D33/$D$36 -> 0.14195389 | F33: =D33-F19 -> 8160.84
C34: Inmueble | D34: =SUMIF($A$5:$A$27,C34,$D$5:$D$27) -> 22519.635 | E34: =D34/$D$36 -> 0.21929026
C35: Hereditas | D35: =SUMIF($A$5:$A$27,C35,$D$5:$D$27) -> 23239.07 | E35: =D35/$D$36 -> 0.22629593
D36: =SUM($D$29:D35) -> 102693.27
C40: RF | D40: =SUMIF($A$5:$A$27,C40,$D$5:$D$27) -> 30416.32 | E40: =D40/$D$48 -> 0.20070654
C41: PP | D41: =SUMIF($A$5:$A$27,C41,$D$5:$D$27) -> 10684.41 | E41: =D41/$D$48 -> 0.070502642
C42: PIAS | D42: =SUMIF($A$5:$A$27,C42,$D$5:$D$27) -> 0 | E42: =D42/$D$48 -> 0
C43: Crypto | D43: =SUMIF($A$5:$A$27,C43,$D$5:$D$27) -> 1256.13 | E43: =D43/$D$48 -> 0.0082887576
C44: CASH | D44: =SUMIF($A$5:$A$27,C44,$D$5:$D$27) -> 14577.71 | E44: =D44/$D$48 -> 0.096193152
C45: Inmueble | D45: =SUMIF($A$5:$A$27,C45,$D$5:$D$27) -> 22519.635 | E45: =D45/$D$48 -> 0.14859911
C46: Casa | D46: =SUMIF($A$5:$A$27,C46,$D$5:$D$27) -> 48852.96 | E46: =D46/$D$48 -> 0.3223634
C47: Hereditas | D47: =SUMIF($A$5:$A$27,C47,$D$5:$D$27) -> 23239.07 | E47: =D47/$D$48 -> 0.1533464
D48: =SUM(D40:D47) -> 151546.23

Sheet 2026-04-06
D2: Date | E2: 45722
A4: Tipo Activo | B4: Activo | C4: Cantidad | D4: NAV | E4: Broker
A5: RF | B5: BBVA | C5: 792 | D5: 7357.84 | E5: BBVA | F5: 9836
A6: RF | B6: IAG | C6: 0 | D6: 0 | E6: BBVA | F6: 5129.85
A7: RF | B7: Grifols | C7: 180 | D7: 1656.72 | E7: BBVA | F7: 1533.24
A8: RF | B8: BKT | C8: 120 | D8: 1637.4 | E8: BKT | F8: 1231.8
A9: RF | B9: OHLA | C9: 5000 | D9: 0 | E9: BKT
A10: PP | B10: Plan Pensiones | D10: 10364.64 | E10: ING
A11: PIAS | B11: SIALP | D11: 0 | E11: NN
A12: PIAS | B12: PIAS | D12: 0 | E12: BKT
A13: RF | B13: Fondos | D13: 15879.3 | E13: BKT | F13: 11791.47
A14: RF | B14: Fondos | D14: 3647.25 | E14: My Investor | F14: 1447.7
A15: Crypto | B15: EARN | D15: 1256.13 | E15: Crypto | O15: 43 | P15: 50
A16: Crypto | B16: Metamask | D16: 0 | E16: Crypto | O16: 38 | P16: 67
A17: Crypto | B17: WANA | D17: 0 | E17: Crypto | O17: 37
A18: Crypto | B18: AXIE | D18: 0 | E18: Crypto
A19: CASH | B19: Comun | D19: =+12023.44/2 -> 6011.72 | E19: RuralVia | F19: =D19+D20 -> 6412.09 | G19: =F19*2 -> 12824.18
A20: CASH | B20: Comun | D20: =800.74/2 -> 400.37 | E20: BKT
A21: CASH | B21: Antonio | D21: 170.69 | E21: BKT
A22: CASH | B22: CASH | D22: 608.41 | E22: SAN
A23: CASH | B23: CASH | D23: 8100.23 | E23: ING
A24: CASH | B24: CASH | D24: 66.01 | E24: BBVA
A25: Inmueble | B25: AQ | D25: =(110000-64714.53)*0.5 -> 22642.735
A26: Hereditas | D26: =(75000+50860.35-5330.04-32000-34658.17)/2 -> 26936.07
A27: Casa | B27: 3C + AB | D27: =175000+10000-135784.22 -> 49215.78
C29: RF | D29: =SUMIF($A$5:$A$27,C29,$D$5:$D$27) -> 30178.51 | E29: =D29/$D$36 -> 0.28274104
C30: PP | D30: =SUMIF($A$5:$A$27,C30,$D$5:$D$27) -> 10364.64 | E30: =D30/$D$36 -> 0.097105823
C31: PIAS | D31: =SUMIF($A$5:$A$27,C31,$D$5:$D$27) -> 0 | E31: =D31/$D$36 -> 0
C32: Crypto | D32: =SUMIF($A$5:$A$27,C32,$D$5:$D$27) -> 1256.13 | E32: =D32/$D$36 -> 0.011768623
C33: CASH | D33: =SUMIF($A$5:$A$27,C33,$D$5:$D$27) -> 15357.43 | E33: =D33/$D$36 -> 0.14388304 | F33: =D33-F19 -> 8945.34
C34: Inmueble | D34: =SUMIF($A$5:$A$27,C34,$D$5:$D$27) -> 22642.735 | E34: =D34/$D$36 -> 0.21213872
C35: Hereditas | D35: =SUMIF($A$5:$A$27,C35,$D$5:$D$27) -> 26936.07 | E35: =D35/$D$36 -> 0.25236277
D36: =SUM($D$29:D35) -> 106735.51
C40: RF | D40: =SUMIF($A$5:$A$27,C40,$D$5:$D$27) -> 30178.51 | E40: =D40/$D$48 -> 0.1935124
C41: PP | D41: =SUMIF($A$5:$A$27,C41,$D$5:$D$27) -> 10364.64 | E41: =D41/$D$48 -> 0.06646075
C42: PIAS | D42: =SUMIF($A$5:$A$27,C42,$D$5:$D$27) -> 0 | E42: =D42/$D$48 -> 0
C43: Crypto | D43: =SUMIF($A$5:$A$27,C43,$D$5:$D$27) -> 1256.13 | E43: =D43/$D$48 -> 0.0080546301
C44: CASH | D44: =SUMIF($A$5:$A$27,C44,$D$5:$D$27) -> 15357.43 | E44: =D44/$D$48 -> 0.098475809
C45: Inmueble | D45: =SUMIF($A$5:$A$27,C45,$D$5:$D$27) -> 22642.735 | E45: =D45/$D$48 -> 0.14519107
C46: Casa | D46: =SUMIF($A$5:$A$27,C46,$D$5:$D$27) -> 49215.78 | E46: =D46/$D$48 -> 0.3155843
C47: Hereditas | D47: =SUMIF($A$5:$A$27,C47,$D$5:$D$27) -> 26936.07 | E47: =D47/$D$48 -> 0.17272104
D48: =SUM(D40:D47) -> 155951.3

Sheet 2026-05-11
D2: Date | E2: 45722
A4: Tipo Activo | B4: Activo | C4: Cantidad | D4: NAV | E4: Broker
A5: RF | B5: BBVA | C5: 792 | D5: 7353.92 | E5: BBVA | F5: 9836
A6: RF | B6: IAG | C6: 0 | D6: 0 | E6: BBVA | F6: 5129.85
A7: RF | B7: Grifols | C7: 180 | D7: 0 | E7: BBVA | F7: 1533.24
A8: RF | B8: BKT | C8: 120 | D8: 1668 | E8: BKT | F8: 1231.8
A9: RF | B9: OHLA | C9: 5000 | D9: 0 | E9: BKT
A10: PP | B10: Plan Pensiones | D10: 11494.69 | E10: ING
A11: PIAS | B11: SIALP | D11: 0 | E11: NN
A12: PIAS | B12: PIAS | D12: 0 | E12: BKT
A13: RF | B13: Fondos | D13: 17669.82 | E13: BKT | F13: 11791.47
A14: RF | B14: Fondos | D14: 4163.76 | E14: My Investor | F14: 1447.7
A15: Crypto | B15: EARN | D15: 1256.13 | E15: Crypto | O15: 43 | P15: 50
A16: Crypto | B16: Metamask | D16: 0 | E16: Crypto | O16: 38 | P16: 67
A17: Crypto | B17: WANA | D17: 0 | E17: Crypto | O17: 37
A18: Crypto | B18: AXIE | D18: 0 | E18: Crypto
A19: CASH | B19: Comun | D19: =+12487.19/2 -> 6243.595 | E19: RuralVia | F19: =D19+D20 -> 6673.34 | G19: =F19*2 -> 13346.68
A20: CASH | B20: Comun | D20: =859.49/2 -> 429.745 | E20: BKT
A21: CASH | B21: Antonio | D21: 3101.47 | E21: BKT
A22: CASH | B22: CASH | D22: 51.23 | E22: SAN
A23: CASH | B23: CASH | D23: 9897.92 | E23: ING
A24: CASH | B24: CASH | D24: 1697.85 | E24: BBVA
A25: Inmueble | B25: AQ | D25: =(110000-64467.76)*0.5 -> 22766.12
A26: Hereditas | D26: =(75000+50921.66-4789.8-31728.1-34394.31)/2 -> 27504.725
A27: Casa | B27: 3C + AB | D27: =175000+10000-135420.72 -> 49579.28
C29: RF | D29: =SUMIF($A$5:$A$27,C29,$D$5:$D$27) -> 30855.5 | E29: =D29/$D$36 -> 0.26761296
C30: PP | D30: =SUMIF($A$5:$A$27,C30,$D$5:$D$27) -> 11494.69 | E30: =D30/$D$36 -> 0.099694642
C31: PIAS | D31: =SUMIF($A$5:$A$27,C31,$D$5:$D$27) -> 0 | E31: =D31/$D$36 -> 0
C32: Crypto | D32: =SUMIF($A$5:$A$27,C32,$D$5:$D$27) -> 1256.13 | E32: =D32/$D$36 -> 0.010894546
C33: CASH | D33: =SUMIF($A$5:$A$27,C33,$D$5:$D$27) -> 21421.81 | E33: =D33/$D$36 -> 0.18579359 | F33: =D33-F19 -> 14748.47
C34: Inmueble | D34: =SUMIF($A$5:$A$27,C34,$D$5:$D$27) -> 22766.12 | E34: =D34/$D$36 -> 0.19745293
C35: Hereditas | D35: =SUMIF($A$5:$A$27,C35,$D$5:$D$27) -> 27504.725 | E35: =D35/$D$36 -> 0.23855134
D36: =SUM($D$29:D35) -> 115298.98
C40: RF | D40: =SUMIF($A$5:$A$27,C40,$D$5:$D$27) -> 30855.5 | E40: =D40/$D$48 -> 0.18714111
C41: PP | D41: =SUMIF($A$5:$A$27,C41,$D$5:$D$27) -> 11494.69 | E41: =D41/$D$48 -> 0.069716228
C42: PIAS | D42: =SUMIF($A$5:$A$27,C42,$D$5:$D$27) -> 0 | E42: =D42/$D$48 -> 0
C43: Crypto | D43: =SUMIF($A$5:$A$27,C43,$D$5:$D$27) -> 1256.13 | E43: =D43/$D$48 -> 0.0076185304
C44: CASH | D44: =SUMIF($A$5:$A$27,C44,$D$5:$D$27) -> 21421.81 | E44: =D44/$D$48 -> 0.12992502
C45: Inmueble | D45: =SUMIF($A$5:$A$27,C45,$D$5:$D$27) -> 22766.12 | E45: =D45/$D$48 -> 0.13807837
C46: Casa | D46: =SUMIF($A$5:$A$27,C46,$D$5:$D$27) -> 49579.28 | E46: =D46/$D$48 -> 0.30070236
C47: Hereditas | D47: =SUMIF($A$5:$A$27,C47,$D$5:$D$27) -> 27504.725 | E47: =D47/$D$48 -> 0.16681839
D48: =SUM(D40:D47) -> 164878.26

Sheet 2026-06-07
D2: Date | E2: 45722
A4: Tipo Activo | B4: Activo | C4: Cantidad | D4: NAV | E4: Broker
A5: RF | B5: BBVA | C5: 792 | D5: 7608.72 | E5: BBVA | F5: 9836
A6: RF | B6: IAG | C6: 0 | D6: 0 | E6: BBVA | F6: 5129.85
A7: RF | B7: Grifols | C7: 180 | D7: 0 | E7: BBVA | F7: 1533.24
A8: RF | B8: BKT | C8: 120 | D8: 1648.8 | E8: BKT | F8: 1231.8
A9: RF | B9: OHLA | C9: 5000 | D9: 0 | E9: BKT
A10: PP | B10: Plan Pensiones | D10: 11938.75 | E10: ING
A11: PIAS | B11: SIALP | D11: 0 | E11: NN
A12: PIAS | B12: PIAS | D12: 0 | E12: BKT
A13: RF | B13: Fondos | D13: 18500.54 | E13: BKT | F13: 11791.47
A14: RF | B14: Fondos | D14: 4461.03 | E14: My Investor | F14: 1447.7
A15: Crypto | B15: EARN | D15: 1405.99 | E15: Crypto | O15: 43 | P15: 50
A16: Crypto | B16: Metamask | D16: 0 | E16: Crypto | O16: 38 | P16: 67
A17: Crypto | B17: WANA | D17: 0 | E17: Crypto | O17: 37
A18: Crypto | B18: AXIE | D18: 0 | E18: Crypto
A19: CASH | B19: Comun | D19: =+12059.37/2 -> 6029.685 | E19: RuralVia
A20: CASH | B20: Comun | D20: =761/2 -> 380.5 | E20: BKT
A21: CASH | B21: Antonio | D21: 4915.48 | E21: BKT
A22: CASH | B22: CASH | D22: 831.2 | E22: SAN
A23: CASH | B23: CASH | D23: 16771.53 | E23: ING
A24: CASH | B24: CASH | D24: 2673.55 | E24: BBVA
A25: Inmueble | B25: AQ | D25: =(110000-64232.91)*0.5 -> 22883.545
A26: Hereditas | D26: =(75000+47352.97-31455.07-34129.46)/2 -> 28384.22
A27: Casa | B27: 3C | D27: =175000-135056.53 -> 39943.47
C29: RF | D29: =SUMIF($A$5:$A$27,C29,$D$5:$D$27) -> 32219.09 | E29: =D29/$D$36 -> 0.25086196
C30: PP | D30: =SUMIF($A$5:$A$27,C30,$D$5:$D$27) -> 11938.75 | E30: =D30/$D$36 -> 0.092956637
C31: PIAS | D31: =SUMIF($A$5:$A$27,C31,$D$5:$D$27) -> 0 | E31: =D31/$D$36 -> 0
C32: Crypto | D32: =SUMIF($A$5:$A$27,C32,$D$5:$D$27) -> 1405.99 | E32: =D32/$D$36 -> 0.010947218
C33: CASH | D33: =SUMIF($A$5:$A$27,C33,$D$5:$D$27) -> 31601.945 | E33: =D33/$D$36 -> 0.24605679 | F33: =D33-F19 -> 31601.945
C34: Inmueble | D34: =SUMIF($A$5:$A$27,C34,$D$5:$D$27) -> 22883.545 | E34: =D34/$D$36 -> 0.17817421
C35: Hereditas | D35: =SUMIF($A$5:$A$27,C35,$D$5:$D$27) -> 28384.22 | E35: =D35/$D$36 -> 0.22100317
D36: =SUM($D$29:D35) -> 128433.54
C40: RF | D40: =SUMIF($A$5:$A$27,C40,$D$5:$D$27) -> 32219.09 | E40: =D40/$D$48 -> 0.19135089
C41: PP | D41: =SUMIF($A$5:$A$27,C41,$D$5:$D$27) -> 11938.75 | E41: =D41/$D$48 -> 0.07090487
C42: PIAS | D42: =SUMIF($A$5:$A$27,C42,$D$5:$D$27) -> 0 | E42: =D42/$D$48 -> 0
C43: Crypto | D43: =SUMIF($A$5:$A$27,C43,$D$5:$D$27) -> 1405.99 | E43: =D43/$D$48 -> 0.0083502492
C44: CASH | D44: =SUMIF($A$5:$A$27,C44,$D$5:$D$27) -> 31601.945 | E44: =D44/$D$48 -> 0.18768563
C45: Inmueble | D45: =SUMIF($A$5:$A$27,C45,$D$5:$D$27) -> 22883.545 | E45: =D45/$D$48 -> 0.13590659
C46: Casa | D46: =SUMIF($A$5:$A$27,C46,$D$5:$D$27) -> 39943.47 | E46: =D46/$D$48 -> 0.23722639
C47: Hereditas | D47: =SUMIF($A$5:$A$27,C47,$D$5:$D$27) -> 28384.22 | E47: =D47/$D$48 -> 0.16857539
D48: =SUM(D40:D47) -> 168377.01

Sheet 2026-07-05
D2: Date | E2: 45722
A4: Tipo Activo | B4: Activo | C4: Cantidad | D4: NAV | E4: Broker
A5: RF | B5: BBVA | C5: 792 | D5: 8914.08 | E5: BBVA
A6: RF | B6: NFLX | C6: 20 | D6: =1553/1.14 -> 1362.2807 | E6: BKT
A7: RF | B7: ORCL | C7: 10 | D7: =1402.7/1.14 -> 1230.4386 | E7: BKT
A8: RF | B8: BKT | C8: 120 | D8: 1809.6 | E8: BKT
A9: RF | B9: OHLA | C9: 5000 | D9: 0 | E9: BKT
A10: PP | B10: Plan Pensiones | D10: 11975.7 | E10: ING
A11: PIAS | B11: SIALP | D11: 0 | E11: NN
A12: PIAS | B12: PIAS | D12: 0 | E12: BKT
A13: RF | B13: Fondos | D13: 18713.36 | E13: BKT
A14: RF | B14: Fondos | D14: 4631.98 | E14: My Investor
A15: Crypto | B15: EARN | D15: 1180.94 | E15: Crypto | O15: 43 | P15: 50
A16: Crypto | B16: Metamask | D16: 0 | E16: Crypto | O16: 38 | P16: 67
A17: Crypto | B17: WANA | D17: 0 | E17: Crypto | O17: 37
A18: Crypto | B18: AXIE | D18: 0 | E18: Crypto
A19: CASH | B19: Comun | D19: =+11686.78/2 -> 5843.39 | E19: RuralVia
A20: CASH | B20: Comun | D20: =1022.09/2 -> 511.045 | E20: BKT
A21: CASH | B21: Antonio | D21: 1150.13 | E21: BKT
A22: CASH | B22: CASH | D22: 1046.38 | E22: SAN
A23: CASH | B23: CASH | D23: 18613.66 | E23: ING
A24: CASH | B24: CASH | D24: 3596.41 | E24: BBVA
A25: Inmueble | B25: AQ | D25: =(110000-63997.4)*0.5 -> 23001.3
A26: Hereditas | D26: =(75000+45164.28-31180.9-33863.62)/2 -> 27559.88
A27: Casa | B27: 3C | D27: =175000-134691.66 -> 40308.34
C29: RF | D29: =SUMIF($A$5:$A$27,C29,$D$5:$D$27) -> 36661.739 | E29: =D29/$D$36 -> 0.27956061
C30: PP | D30: =SUMIF($A$5:$A$27,C30,$D$5:$D$27) -> 11975.7 | E30: =D30/$D$36 -> 0.091319563
C31: PIAS | D31: =SUMIF($A$5:$A$27,C31,$D$5:$D$27) -> 0 | E31: =D31/$D$36 -> 0
C32: Crypto | D32: =SUMIF($A$5:$A$27,C32,$D$5:$D$27) -> 1180.94 | E32: =D32/$D$36 -> 0.0090051459
C33: CASH | D33: =SUMIF($A$5:$A$27,C33,$D$5:$D$27) -> 30761.015 | E33: =D33/$D$36 -> 0.2345652 | F33: =D33-F19 -> 30761.015
C34: Inmueble | D34: =SUMIF($A$5:$A$27,C34,$D$5:$D$27) -> 23001.3 | E34: =D34/$D$36 -> 0.17539423
C35: Hereditas | D35: =SUMIF($A$5:$A$27,C35,$D$5:$D$27) -> 27559.88 | E35: =D35/$D$36 -> 0.21015525
D36: =SUM($D$29:D35) -> 131140.57
C40: RF | D40: =SUMIF($A$5:$A$27,C40,$D$5:$D$27) -> 36661.739 | E40: =D40/$D$48 -> 0.21383477
C41: PP | D41: =SUMIF($A$5:$A$27,C41,$D$5:$D$27) -> 11975.7 | E41: =D41/$D$48 -> 0.069849961
C42: PIAS | D42: =SUMIF($A$5:$A$27,C42,$D$5:$D$27) -> 0 | E42: =D42/$D$48 -> 0
C43: Crypto | D43: =SUMIF($A$5:$A$27,C43,$D$5:$D$27) -> 1180.94 | E43: =D43/$D$48 -> 0.0068879993
C44: CASH | D44: =SUMIF($A$5:$A$27,C44,$D$5:$D$27) -> 30761.015 | E44: =D44/$D$48 -> 0.17941796
C45: Inmueble | D45: =SUMIF($A$5:$A$27,C45,$D$5:$D$27) -> 23001.3 | E45: =D45/$D$48 -> 0.13415833
C46: Casa | D46: =SUMIF($A$5:$A$27,C46,$D$5:$D$27) -> 40308.34 | E46: =D46/$D$48 -> 0.23510408
C47: Hereditas | D47: =SUMIF($A$5:$A$27,C47,$D$5:$D$27) -> 27559.88 | E47: =D47/$D$48 -> 0.16074689
D48: =SUM(D40:D47) -> 171448.91

Sheet Sheet9
C4: RF | D4: BBVA | E4: 792 | F4: 10503.9 | G4: BBVA | I4: RF | J4: BBVA | K4: 792 | L4: 9757.44 | M4: BBVA | O4: =F4-L4 -> 746.46
C5: RF | D5: IAG | E5: 650 | F5: 6599.18 | G5: BBVA | I5: RF | J5: IAG | K5: 650 | L5: 5407.05 | M5: BBVA | O5: =F5-L5 -> 1192.13
C6: RF | D6: Grifols | E6: 180 | F6: 1868.4 | G6: BBVA | I6: RF | J6: Grifols | K6: 180 | L6: 1546.56 | M6: BBVA | O6: =F6-L6 -> 321.84
C7: RF | D7: BKT | E7: 120 | F7: 1380 | G7: BKT | I7: RF | J7: BKT | K7: 120 | L7: 1263 | M7: BKT | O7: =F7-L7 -> 117
C8: RF | D8: OHLA | E8: 5000 | F8: 0 | G8: BKT | I8: RF | J8: OHLA | K8: 5000 | L8: 0 | M8: BKT | O8: =F8-L8 -> 0
C9: PP | D9: Plan Pensiones | F9: 8311.38 | G9: BKT | I9: PP | J9: Plan Pensiones | L9: 7892 | M9: BKT | O9: =F9-L9 -> 419.38
C10: PIAS | D10: SIALP | F10: 0 | G10: NN | I10: PIAS | J10: SIALP | L10: 0 | M10: NN | O10: =F10-L10 -> 0
C11: PIAS | D11: PIAS | F11: 0 | G11: BKT | I11: PIAS | J11: PIAS | L11: 0 | M11: BKT | O11: =F11-L11 -> 0
C12: RF | D12: Fondos | F12: 13206.1 | G12: BKT | I12: RF | J12: Fondos | L12: 12381.2 | M12: BKT | O12: =F12-L12 -> 824.9
C13: RF | D13: Fondos | F13: 1877.43 | G13: My Investor | I13: RF | J13: Fondos | L13: 1645.65 | M13: My Investor | O13: =F13-L13 -> 231.78
C14: Crypto | D14: EARN | F14: 2184.9 | G14: Crypto | I14: Crypto | J14: EARN | L14: 1935.76 | M14: Crypto | O14: =F14-L14 -> 249.14
C15: Crypto | D15: Metamask | F15: 0 | G15: Crypto | I15: Crypto | J15: Metamask | L15: 0 | M15: Crypto | O15: =F15-L15 -> 0
C16: Crypto | D16: WANA | F16: 0 | G16: Crypto | I16: Crypto | J16: WANA | L16: 0 | M16: Crypto | O16: =F16-L16 -> 0
C17: Crypto | D17: AXIE | F17: 0 | G17: Crypto | I17: Crypto | J17: AXIE | L17: 0 | M17: Crypto | O17: =F17-L17 -> 0
C18: CASH | D18: Comun | F18: 3824.93 | G18: RuralVia | I18: CASH | J18: Comun | L18: 3384.08 | M18: RuralVia | O18: =F18-L18 -> 440.85
C19: CASH | D19: Comun | F19: 970.235 | G19: BKT | I19: CASH | J19: Comun | L19: 904.895 | M19: BKT | O19: =F19-L19 -> 65.34
C20: CASH | D20: Antonio | F20: 578.32 | G20: BKT | I20: CASH | J20: Antonio | L20: 1795 | M20: BKT | O20: =F20-L20 -> -1216.68
... C23: CASH | D23: CASH | F23: 1797.8 | G23: BBVA | I23: CASH | J23: CASH | L23: 2308.14 | M23: BBVA | O23: =F23-L23 -> -510.34
C24: Inmueble | D24: AQ | F24: 21424.52 | I24: Inmueble | J24: AQ | L24: 21304.25 | O24: =F24-L24 -> 120.27
C25: Hereditas | F25: 17738.495 | I25: Hereditas | L25: 17219.355 | O25: =F25-L25 -> 519.14
C26: Casa | D26: 3C | F26: 35850.37 | I26: Casa | J26: 3C | L26: 35541.31 | O26: =F26-L26 -> 309.06
